{
  "codigo_produto": "201",
  "url": "https://www.tdpwines.com.br/vinho-branco-portugues-regateiro-junior-bairrada",
  "titulo": "Regateiro Jr Branco Bairrada DOC 2021",
  "descricao_geral": "92 pontos DecanterRegateiro é, dentro da Lusovini, um projeto na Bairrada capitaneado por um de seus sócio-fundadores, Casimiro Gomes em homenagem a seu avô Manuel Gomes Regateiro Júnior. Manuel, que residia em Aguada de Cima, transformou os solos argilosos em azulejos tradicionais e também em parreirais, dando origem a vinhos que contam e fazem parte da identidade da Bairrada, elaborados principalmente com a casta Baga. Em nome de uma relação familiar com o vinho de mais de 350 anos, Casimiro continua o legado do seu avô com os vinhos do projeto Regateiro.Regateiro Jr Bairrada DOC marca a entrada do filho de Casimiro, Carlos, no projeto. Este branco de produção limitada, com apenas 3000 garrafas, traz no seu corte as castas tradicionais da região: Arinto, Bical e Maria Gomes. Não passa por madeira, porém seu estágio em tanques de inox com battonage lhe dá complexidade e estrutura interessantes. É elegante e perfumado, com notas sobretudo cítricas que também se confirmam em boca. Tem acidez presente e que marca seu longo final.Regateiro Jr Branco é ótimo para ser consumido com frutos do mar e pratos mais leves da Bairrada, como peixes grelhados, frutos do mar e saladas. CaracteristicasProdutor LusoviniPais PortugalRegião BairradaTipo BrancoUva Arinto, Bical e Maria GomesVolume 750mlSafra 2021Teor Alcoólico 12%Temperatura de Serviço 8 a 10°CVinificação Fermentação em inox a baixas temperaturas por 30 dias.Maturação Estágio em inox com battonage.Corpo MédioPotencial de Guarda 5 anosHarmonizações Pratos à base de peixe, carnes brancas ou grelhados. Baixar Ficha Técnica Baixar Imagem",
  "caracteristicas": {
    "produtor": "Lusovini",
    "pais": "Ver País Argentina Patagonia Chile Portugal Brasil Espanha Ribera del Duero Itália Piemonte Abruzzo Sicilia Provincia de Taranto Toscana França África do Sul",
    "regiao": "Bairrada",
    "tipo": "Branco",
    "uva": "Arinto, Bical e Maria Gomes",
    "volume_ml": 750,
    "safra": "2021",
    "teor_alcoolico_percent": 12.0,
    "temperatura_servico_c": "8 a 10°C",
    "vinificacao": "Fermentação em inox a baixas temperaturas por 30 dias.",
    "maturacao": "Estágio em inox com battonage.",
    "corpo": "Médio",
    "potencial_guarda_anos": "5 anos",
    "harmonizacoes": [
      "Pratos à base de peixe",
      "carnes brancas ou grelhados"
    ]
  },
  "midia": {
    "imagem_principal_url": "https://images.tcdn.com.br/img/img_prod/791130/regateiro_jr_branco_bairrada_doc_2021_201_2_2df5ca07610545ffa96abe2e373b93d6.jpg",
    "ficha_tecnica_url": "https://drive.usercontent.google.com/u/2/uc?id=1NyN1aYq-xdkWbYA60E1X9x-57rlyxRWN&export=download"
  }
}