{
  "codigo_produto": "265",
  "url": "https://www.tdpwines.com.br/vinho-tinto-espanhol-tardencuba-crianza-toro",
  "titulo": "Tardencuba DO Toro Crianza Tinto 2018",
  "descricao_geral": "90 pontos Robert ParkerTardencuba, localizada em Venialbo, no coração da DO Toro, é um pequeno empreendimento familiar que há três gerações produz vinhos de exceção. A altitude dos apenas três hectares de vinhas pré-filoxericas, junto às noites frias, faz as uvas da família Ramos amadurecem por completo, originando vinhos concentrados, potentes e longevos.Os &#39;Crianza&#39;, pela legislação espanhola, devem envelhecer um mínimo de dois anos após a colheita, sendo ao menos seis meses em madeira. Este 100% Tinta de Toro de vinhedos antigos passa 12 meses em carvalho francês e mais outro ano em cave. Seu aroma é bastante complexo, com fruta vermelha e negra madura, cacau, balsâmico e medicinal. Em boca, é carnoso, quente, muito encorpado.É um excelente vinho para acompanhar carnes de caça e queijos curados. CaracteristicasProdutor TardencubaPais EspanhaRegião ZamoraTipo TintoUva 100% Tinta de Toro, videiras com mais de 60 anos.Volume 750mlSafra 2018Teor Alcoólico 15%Temperatura de Serviço 14°CVinificação Fermentação tradicional. Maceração de 25 dias com temperatura controlada em 28ºC.Maturação 12 meses em carvalho mais 12 meses em garrafa.Corpo IntensoPotencial de Guarda 10 anosHarmonizações Carnes vermelhas grelhadas, queijos de massa dura. Baixar Ficha Técnica Baixar Imagem",
  "caracteristicas": {
    "produtor": "Tardencuba",
    "pais": "Ver País Argentina Patagonia Chile Portugal Brasil Espanha Ribera del Duero Itália Piemonte Abruzzo Sicilia Provincia de Taranto Toscana França África do Sul",
    "regiao": "Zamora",
    "tipo": "Tinto",
    "uva": "100% Tinta de Toro, videiras com mais de 60 anos.",
    "volume_ml": 750,
    "safra": "2018",
    "teor_alcoolico_percent": 15.0,
    "temperatura_servico_c": "14°C",
    "vinificacao": "Fermentação tradicional. Maceração de 25 dias com temperatura controlada em 28ºC.",
    "maturacao": "12 meses em carvalho mais 12 meses em garrafa.",
    "corpo": "Intenso",
    "potencial_guarda_anos": "10 anos",
    "harmonizacoes": [
      "Carnes vermelhas grelhadas",
      "queijos de massa dura"
    ]
  },
  "midia": {
    "imagem_principal_url": "https://images.tcdn.com.br/img/img_prod/791130/tardencuba_do_toro_crianza_tinto_2017_265_1_a09f24159254e77753f40c449dfc1fdb_20221003162202.png",
    "ficha_tecnica_url": "https://drive.usercontent.google.com/u/2/uc?id=1Ox_x6SHUHYj1a4eP6-AWcXIDHFfguLTi&export=download"
  }
}