{
  "codigo_produto": "145",
  "url": "https://www.tdpwines.com.br/vinho-branco-portugues-pedra-cancela-vinha-da-fidalga-encruzado",
  "titulo": "Pedra Cancela Vinha da Fidalga Encruzado Branco 2022",
  "descricao_geral": "17,5 pontos Revista de VinhosPedra Cancela, mesmo com sua pouca idade, já é considerado por alguns críticos portugueses como um dos projetos mais interessantes do Dão. Capitaneado por João Paulo Gouveia em parceria com a grandiosa Lusovini, produz vinhos que exaltam as melhores características da região. A Vinha da Fidalga, um terreno onde natureza e vinhedos fundem-se na busca de equilíbrio, marca uma nova fase do projeto, já com vinhos maravilhosos, como este Encruzado. Elaborado 100% com a casta branca mais representativa do Dão, o Vinha da Fidalga foi um sucesso desde sua primeira safra, em 2018, que conquistou o prêmio de melhor vinho do Dão e um dos melhores de Portugal pelo guia Copo & Alma, de Aníbal Coutinho. As notas cítricas, principalmente de laranja e toranja, se fundem com um toque mineral característico e muito atrativo.Com grande potencial de guarda, este Encruzado é harmonização perfeita para peixes mais &#39;gordos&#39;, como robalo, bacalhau e pratos com molhos brancos. CaracteristicasProdutor LusoviniPais PortugalRegião DãoTipo BrancoUva 100% EncruzadoVolume 750mlSafra 2022Teor Alcoólico 13,5%Temperatura de Serviço 8 a 10°CVinificação Fermentação com temperatura controlada a 14-16ºC.Maturação 3 meses em barricas de carvalho francês de segundo e terceiro usos, com batonnage.Corpo MédioPotencial de Guarda 6 a 8 anosHarmonizações Carnes brancas, bacalhau, peixes gordos, como salmão, e saladas. Baixar Ficha Técnica Baixar Imagem",
  "caracteristicas": {
    "produtor": "Lusovini",
    "pais": "Ver País Argentina Patagonia Chile Portugal Brasil Espanha Ribera del Duero Itália Piemonte Abruzzo Sicilia Provincia de Taranto Toscana França África do Sul",
    "regiao": "Dão",
    "tipo": "Branco",
    "uva": "100% Encruzado",
    "volume_ml": 750,
    "safra": "2022",
    "teor_alcoolico_percent": 13.5,
    "temperatura_servico_c": "8 a 10°C",
    "vinificacao": "Fermentação com temperatura controlada a 14-16ºC.",
    "maturacao": "3 meses em barricas de carvalho francês de segundo e terceiro usos, com batonnage.",
    "corpo": "Médio",
    "potencial_guarda_anos": "6 a 8 anos",
    "harmonizacoes": [
      "Carnes brancas",
      "bacalhau",
      "peixes gordos",
      "como salmão",
      "saladas"
    ]
  },
  "midia": {
    "imagem_principal_url": "https://images.tcdn.com.br/img/img_prod/791130/pedra_cancela_vinha_da_fidalga_encruzado_branco_2019_145_1_20221003162152.png",
    "ficha_tecnica_url": "https://drive.usercontent.google.com/u/2/uc?id=1L-RYy5CECr6djIreMtQm0nd9gMTSKwA2&export=download"
  }
}