{
  "codigo_produto": "245",
  "url": "https://www.tdpwines.com.br/vinho-tinto-espanhol-tardencuba-anada-selecionada-toro",
  "titulo": "Tardencuba DO Toro Selección Tinto 2022",
  "descricao_geral": "Tardencuba, localizada em Venialbo, no coração da DO Toro, é um pequeno empreendimento familiar que há três gerações produz vinhos de exceção. A altitude dos apenas três hectares de vinhas pré-filoxericas, junto às noites frias, faz as uvas da família Ramos amadurecem por completo, originando vinhos concentrados, potentes e longevos.Selección é o vinho mais jovem da casa e um dos únicos a não passar por envelhecimento em madeira. 100% Tinta de Toro de vinhedos com mais de 60 anos, este vinho tem uma brilhante cor púrpura, escura e intensa. No nariz, a fruta domina, principalmente as negras e vermelhas, junto a um toque de alcaçuz. Na boca, é um vinho redondo, de bom corpo e longo final.Sem passagem por madeira, este tinto mais fresco desta zona quente é perfeito para acompanhar tábua de frios, carnes magras grelhadas, pizzas e hamburgers. CaracteristicasProdutor TardencubaPais EspanhaRegião ZamoraTipo TintoUva 100% Tinta de Toro, videiras com mais de 60 anos.Volume 750mlSafra 2022Teor Alcoólico 14,5%Temperatura de Serviço 14°CVinificação Fermentação tradicional com temperatura controlada em 28ºC.Maturação Em tanques de aço inoxCorpo MédioPotencial de Guarda 5 anosHarmonizações Carnes vermelhas grelhadas, lasanha de beringela. Baixar Ficha Técnica Baixar Imagem",
  "caracteristicas": {
    "produtor": "Tardencuba",
    "pais": "Ver País Argentina Patagonia Chile Portugal Brasil Espanha Ribera del Duero Itália Piemonte Abruzzo Sicilia Provincia de Taranto Toscana França África do Sul",
    "regiao": "Zamora",
    "tipo": "Tinto",
    "uva": "100% Tinta de Toro, videiras com mais de 60 anos.",
    "volume_ml": 750,
    "safra": "2022",
    "teor_alcoolico_percent": 14.5,
    "temperatura_servico_c": "14°C",
    "vinificacao": "Fermentação tradicional com temperatura controlada em 28ºC.",
    "maturacao": "Em tanques de aço inox",
    "corpo": "Médio",
    "potencial_guarda_anos": "5 anos",
    "harmonizacoes": [
      "Carnes vermelhas grelhadas",
      "lasanha de beringela"
    ]
  },
  "midia": {
    "imagem_principal_url": "https://images.tcdn.com.br/img/img_prod/791130/tardencuba_do_toro_seleccion_tinto_2020_245_1_333fdeb8fa6f6fd64a3a62477b9a40ee_20221003162201.png",
    "ficha_tecnica_url": "https://drive.usercontent.google.com/u/2/uc?id=1OrpfeSSiH_s9HRBUR0ulZDlr3xrVBPxf&export=download"
  }
}