{
  "codigo_produto": "vinho-tinto-portugues-quinta-de-pinhancos-colheita-dao",
  "url": "https://www.tdpwines.com.br/vinho-tinto-portugues-quinta-de-pinhancos-colheita-dao",
  "titulo": "VIN POR QTA DE PINHANÇOS COLHEITA DÃO TINTO 6X750ML 2016Referência:103240Marca:LusoviniSeja o primeiro a opinar",
  "descricao_geral": "Os vinhos de Alvaro de Castro representam como poucos a região do Dão. Defensor da terra onde nasceu, cresceu e prosperou como enólogo e produtor, Alvaro busca elaborar vinhos fiéis ao seu solo, elaborado com castas regionais e tradicionalmente aptos à guarda. Quinta de Pinhanços Colheita é um tinto que segue à risca a fórmula. Corte das variedades Tinta Roriz, Touriga Nacional e Alfrocheiro, estagia por seis meses em barricas de carvalho francês de segundo uso. No nariz, bastante fruta vermelha madura, cerejas principalmente, especiarias e algum tostado. Em boca, é macio e agradável, com os taninos bem integrados à madeira. Final longo. Harmoniza muito bem com pratos à base de carne vermelha e queijos de cura média, como Gruyère e Serra da Estrela. Caracteristicas Produtor Álvaro de Castro e Lusovini Pais Portugal Região Dão Tipo Tinto Uva Touriga Nacional, Tinta Roriz, Jaen e Alfrocheiro Volume 750ml Safra 2016 Teor Alcoólico 13% Temperatura de Serviço 14 a 16°C Vinificação Extração pré-fermentativa a baixa temperatura por 24h. Fermentação a temperatura controlada entre 24 e 26ºC. Maturação 8 meses em barricas de carvalho francês. Corpo Médio Potencial de Guarda 6 a 8 anos Harmonizações Carnes vermelhas ensopadas, pernil de cordeiro, risoto de cogumelos, queijos de massa mole. Baixar Ficha Técnica Baixar Imagem",
  "caracteristicas": {
    "produtor": "Álvaro de Castro e Lusovini",
    "pais": "Ver País Argentina Patagonia Chile Portugal Brasil Espanha Ribera del Duero Itália Piemonte Abruzzo Sicilia Provincia de Taranto Toscana França África do Sul",
    "regiao": "Dão",
    "tipo": "Tinto",
    "uva": "Touriga Nacional, Tinta Roriz, Jaen e Alfrocheiro",
    "volume_ml": 750,
    "safra": "2016",
    "teor_alcoolico_percent": 13.0,
    "temperatura_servico_c": "14 a 16°C",
    "vinificacao": "Extração pré-fermentativa a baixa temperatura por 24h. Fermentação a temperatura controlada entre 24 e 26ºC.",
    "maturacao": "8 meses em barricas de carvalho francês.",
    "corpo": "Médio",
    "potencial_guarda_anos": "6 a 8 anos",
    "harmonizacoes": [
      "muito bem com pratos à base de carne vermelha",
      "queijos de cura média",
      "como Gruyère",
      "Serra da Estrela"
    ]
  },
  "midia": {
    "imagem_principal_url": "https://images.tcdn.com.br/img/img_prod/791130/vin_por_qta_de_pinhancos_colheita_dao_tinto_6x750ml_313_1_c06a13469a89f3dc4fb43fb4cfa8695c_20221003162148.png",
    "ficha_tecnica_url": "https://drive.usercontent.google.com/u/2/uc?id=1LgvEP1pI7Q8rBPdypD1T0SGtwkVRNNpT&export=download"
  }
}