{
  "codigo_produto": "295",
  "url": "https://www.tdpwines.com.br/vinho-tinto-argentino-tapiz-alta-collection-cabernet-sauvignon",
  "titulo": "Tapiz Alta Collection Cabernet Sauvignon 2021",
  "descricao_geral": "O Tapiz Alta Cabernet Sauvignon já foi chamado pela Wine Advocate como um &#39;Cabernet Sauvignon de clima frio de manual&#39;. Elaborado pela dupla Fabian Valenzuela, enólogo-chefe com 30 anos de casa, e Jean Claude Berrouet, consultor exclusivo da Tapiz e ex-enólogo do Chateau Pétrus, na França, este vinho une potência e corpo com a clássica acidez do Vale do Uco.Este Cabernet Sauvignon da linha Alta Collection é elaborado com uvas de San Pablo, a 1350m de altitude, com um clima mais fresco e noites frias. O vinho é intenso, com notas de frutas vermelhas, grafite, côco e café. Encorpado, tem taninos firmes e muito finos, com um longo potencial de guarda. Passa 10 meses em barricas de carvalho francês (90%) e americano (10%) de primeiro e segundo usos.Este Cabernet Sauvignon da Tapiz pede pratos fortes e untuosos, preparados com carnes vermelhas. Churrasco de costela ou vazio e cozidos de carne vermelha, como vaca atolada e barreado, são ótimas harmonizações. CaracteristicasProdutor TapizPais ArgentinaRegião Vale do Uco, MendozaTipo TintoUva 100% Cabernet SauvignonVolume 750mlSafra 2021Teor Alcoólico 14,1%Temperatura de Serviço 16°CVinificação 5 dias de maceração préfermentativa a 8º - 9ºC. 14 dias de fermentação com temperatura controlada.Maturação 10 meses em carvalho francês (90%) e americano (10%) de primeiro e segundo usos.Corpo MédioPotencial de Guarda 12 anosHarmonizações Costela e vazio assados, barreado, vaca atolada, carne de panela. Baixar Ficha Técnica Baixar Imagem",
  "caracteristicas": {
    "produtor": "Tapiz",
    "pais": "Ver País Argentina Patagonia Chile Portugal Brasil Espanha Ribera del Duero Itália Piemonte Abruzzo Sicilia Provincia de Taranto Toscana França África do Sul",
    "regiao": "Vale do Uco, Mendoza",
    "tipo": "Tinto",
    "uva": "100% Cabernet Sauvignon",
    "volume_ml": 750,
    "safra": "2021",
    "teor_alcoolico_percent": 14.1,
    "temperatura_servico_c": "16°C",
    "vinificacao": "5 dias de maceração préfermentativa a 8º - 9ºC. 14 dias de fermentação com temperatura controlada.",
    "maturacao": "10 meses em carvalho francês (90%) e americano (10%) de primeiro e segundo usos.",
    "corpo": "Médio",
    "potencial_guarda_anos": "12 anos",
    "harmonizacoes": [
      "Costela",
      "vazio assados",
      "barreado",
      "vaca atolada",
      "carne de panela"
    ]
  },
  "midia": {
    "imagem_principal_url": "https://images.tcdn.com.br/img/img_prod/791130/vin_arg_tapiz_alta_collection_cabernet_sauvignon_tto_6x750ml_295_1_bd1c6d69b1847b9f25de8e8f787fcb5c_20221003162148.jpg",
    "ficha_tecnica_url": "https://drive.usercontent.google.com/u/2/uc?id=1ILNpLWBNt6AuyTVqto3GN2h_FXKmzsGF&export=download"
  }
}