{
  "codigo_produto": "319",
  "url": "https://www.tdpwines.com.br/vinho-tinto-italiano-passio-apassimento-nero-d-avola",
  "titulo": "Passio Nero D'Avola Apassimento Sicilia DOC 2021",
  "descricao_geral": "Passio traz à típica Nero D&rsquo;Avola uma leitura muito interessante. O vinho é elaborado com um breve apassimento de suas uvas, colhidas sobremaduras cerca de 15 dias após o final da colheita. O vinho ganha em estrutura e aromas, apresentando um rico paladar aveludado.Passio é um tinto intenso, volumoso e sedoso. Elaborado com uvas colhidas sobremaduras, as notas aromáticas de fruta negra madura e compotada dominam, junto a especiarias.Em boca, Passio ganha muito em corpo e volume com esta técnica, porém ser perder em frescor, já que o produtor optou por não envelhecer o vinho em madeira. É um rótulo para quem gosta de vinhos diferentes e de bom corpo. CaracteristicasProdutor SettesoliPais ItáliaRegião SiciliaTipo TintoUva 100% Nero D&rsquo;AvolaVolume 750mlSafra 2021Teor Alcoólico 13,5%Temperatura de Serviço 14°CVinificação Fermentação tradicional com temperatura controlada.Maturação Tanques de aço inoxCorpo MédioPotencial de Guarda 5 anosHarmonizações Carne vermelha grelhada, massas com molho vermelho. Baixar Ficha Técnica Baixar Imagem",
  "caracteristicas": {
    "produtor": "Settesoli",
    "pais": "Ver País Argentina Patagonia Chile Portugal Brasil Espanha Ribera del Duero Itália Piemonte Abruzzo Sicilia Provincia de Taranto Toscana França África do Sul",
    "regiao": "Sicilia",
    "tipo": "Tinto",
    "uva": "100% Nero D’Avola",
    "volume_ml": 750,
    "safra": "2021",
    "teor_alcoolico_percent": 13.5,
    "temperatura_servico_c": "14°C",
    "vinificacao": "Fermentação tradicional com temperatura controlada.",
    "maturacao": "Tanques de aço inox",
    "corpo": "Médio",
    "potencial_guarda_anos": "5 anos",
    "harmonizacoes": [
      "Carne vermelha grelhada",
      "massas com molho vermelho"
    ]
  },
  "midia": {
    "imagem_principal_url": "https://images.tcdn.com.br/img/img_prod/791130/passio_nero_davola_apassimento_sicilia_doc_2020_319_1_b72c5db15f5a823b60d269c9f5353d2b.png",
    "ficha_tecnica_url": "https://drive.usercontent.google.com/u/2/uc?id=1iX3A9MZldj4RyA93y3ApemNHLN9w8eCm&export=download"
  }
}