{
  "codigo_produto": "297",
  "url": "https://www.tdpwines.com.br/vinho-tinto-argentino-luna-cabernet-sauvignon",
  "titulo": "Luna Cabernet Sauvignon 2022",
  "descricao_geral": "Single vineyard, com uvas provenientes de Agrelo, este Cabernet Sauvignon de Luna segue a receita da Finca La Anita em elaborar vinhos potentes, tânicos e de longa guarda. Os vinhedos da vinícola, a primeira &#39;bodega&#39; boutique da Argentina e da região, estão localizados ao lado da famosa Catena Zapata, em uma zona de extrema qualidade.Um Cabernet Sauvignon de ótima tipicidade, Luna tem sobretudo notas de frutas negras em seu aroma, complementadas por especiarias, compota de frutas e baunilha. Em boca, tem excelente volume, com taninos presentes, corpo médio para mais e muita elegência. Passa nove meses em barricas de carvalho francês e americano de segundo uso e tosta média.Um Cabernet Sauvignon muito versátil, que pode acompanhar carnes vermelhas assadas, como fraldinha e maminha, hamburger, e massas com molho de carne. CaracteristicasProdutor Finca La AnitaPais ArgentinaRegião Agrelo, MendozaTipo TintoUva 100% Cabernet SauvignonVolume 750mlSafra 2022Teor Alcoólico 13,3%Temperatura de Serviço 16°CVinificação Fermentação em tanques de inox, com leveduras selecionadas, por 10 dias. Fermentação malolática espontânea com controle de temperatura.Maturação 9 meses em barricas francesas e americanas de segundo uso.Corpo MédioPotencial de Guarda 7 anosHarmonizações Churrasco, massas com molho de carne, hamburger. Baixar Ficha Técnica Baixar Imagem",
  "caracteristicas": {
    "produtor": "Finca La Anita",
    "pais": "Ver País Argentina Patagonia Chile Portugal Brasil Espanha Ribera del Duero Itália Piemonte Abruzzo Sicilia Provincia de Taranto Toscana França África do Sul",
    "regiao": "Agrelo, Mendoza",
    "tipo": "Tinto",
    "uva": "100% Cabernet Sauvignon",
    "volume_ml": 750,
    "safra": "2022",
    "teor_alcoolico_percent": 13.3,
    "temperatura_servico_c": "16°C",
    "vinificacao": "Fermentação em tanques de inox, com leveduras selecionadas, por 10 dias. Fermentação malolática espontânea com controle de temperatura.",
    "maturacao": "9 meses em barricas francesas e americanas de segundo uso.",
    "corpo": "Médio",
    "potencial_guarda_anos": "7 anos",
    "harmonizacoes": [
      "Churrasco",
      "massas com molho de carne",
      "hamburger"
    ]
  },
  "midia": {
    "imagem_principal_url": "https://images.tcdn.com.br/img/img_prod/791130/luna_cabernet_sauvignon_2020_297_1_f143a8f47fdb44668a26194d9ba9929b_20221003162147.jpg",
    "ficha_tecnica_url": "https://drive.usercontent.google.com/u/2/uc?id=1EO7HaGxxKFlFp-Di6JNRBozy6NrjmkSv&export=download"
  }
}