{
  "codigo_produto": "395",
  "url": "https://www.tdpwines.com.br/vinho-tinto-chileno-veramonte-gran-reserva-cabernet-sauvignon",
  "titulo": "Veramonte Gran Reserva Cabernet Sauvignon 2021",
  "descricao_geral": "Um grande tinto, intenso e encorpado, com notas de frutas vermelhas, pretas, couro e baunilha. Longo final.. Certificadamente orgânico. CaracteristicasProdutor VeramontePais ChileRegião ColchaguaTipo TintoUva 100% Cabernet SauvignonVolume 750mlSafra 2021Teor Alcoólico 14%Temperatura de Serviço 14 a 16°CVinificação Maceração a frio por 5 dias, fermentação com leveduras nativas. Maceração pósfermentativa por 10 dias.Maturação 12 meses em barricas de carvalho francês.Corpo EncorpadoPotencial de Guarda 5 anosHarmonizações Cortes intensos de carne vermelha, como costela e fraldinha. Queijos duros. Baixar Ficha Técnica Baixar Imagem",
  "caracteristicas": {
    "produtor": "Veramonte",
    "pais": "Ver País Argentina Patagonia Chile Portugal Brasil Espanha Ribera del Duero Itália Piemonte Abruzzo Sicilia Provincia de Taranto Toscana França África do Sul",
    "regiao": "Colchagua",
    "tipo": "Tinto",
    "uva": "100% Cabernet Sauvignon",
    "volume_ml": 750,
    "safra": "2021",
    "teor_alcoolico_percent": 14.0,
    "temperatura_servico_c": "14 a 16°C",
    "vinificacao": "Maceração a frio por 5 dias, fermentação com leveduras nativas. Maceração pósfermentativa por 10 dias.",
    "maturacao": "12 meses em barricas de carvalho francês.",
    "corpo": "Encorpado",
    "potencial_guarda_anos": "5 anos",
    "harmonizacoes": [
      "Cortes intensos de carne vermelha",
      "como costela",
      "fraldinha. Queijos duros"
    ]
  },
  "midia": {
    "imagem_principal_url": "https://images.tcdn.com.br/img/img_prod/791130/veramonte_gran_reserva_cabernet_sauvignon_2021_395_1_00cc949222db9dd3d7005e1bc65ba1b1.png",
    "ficha_tecnica_url": "https://drive.usercontent.google.com/uc?id=1KQoVy57c6Leb19qBt1LhajFInbencD0A&export=download"
  }
}