{
  "codigo_produto": "225",
  "url": "https://www.tdpwines.com.br/vinho-tinto-argentino-sol-sul-malbec",
  "titulo": "Sol Sul Malbec Tinto 2022",
  "descricao_geral": "O sol brilha mais ao sul do continente americano! Os vinhos da linha Sol Sul foram criados com muito cuidado pelo enólogo Tiago Dal Pizzol para expressarem as melhores características varietais de suas uvas, trazendo sempre varietais que são grandes clássicos do mundo do vinho.Este Malbec argentino vem da área mais nobre e conhecida do país vizinho, Mendoza, e fielmente apresenta tudo o que se espera em um vinho da região. Com breve passagem por barricas de carvalho, é um vinho extremamente fácil de beber, com aroma que destaca um conjunto de frutas negras e vermelhas maduras, como cerejas e ameixas, e uma nota floral muito fresca. Em boca, é um vinho muito agradável, com as notas de frutas se confirmando, junto à sensação sedosa e macia do vinho.Pronto para beber, este vinho é muito versátil na harmonização, podendo acompanhar desde um bom churrasco até comidas mais leves, como pizzas e massas com molho vermelho. CaracteristicasProdutor TDP WinesPais ArgentinaRegião MendozaTipo TintoUva 100% MalbecVolume 750mlSafra 2022Teor Alcoólico 13,5%Temperatura de Serviço 14 a 16°CVinificação Vinificação tradicional em tanques com controle de temperatura (25ºC).Maturação 3 meses em barricas de carvalho de segundo e terceiro usos.Corpo MédioPotencial de Guarda 3 a 5 anosHarmonizações Carnes vermelhas assadas, beringela parmeggiana, queijo parmesão. Baixar Ficha Técnica Baixar Imagem",
  "caracteristicas": {
    "produtor": "TDP Wines",
    "pais": "Ver País Argentina Patagonia Chile Portugal Brasil Espanha Ribera del Duero Itália Piemonte Abruzzo Sicilia Provincia de Taranto Toscana França África do Sul",
    "regiao": "Mendoza",
    "tipo": "Tinto",
    "uva": "100% Malbec",
    "volume_ml": 750,
    "safra": "2022",
    "teor_alcoolico_percent": 13.5,
    "temperatura_servico_c": "14 a 16°C",
    "vinificacao": "Vinificação tradicional em tanques com controle de temperatura (25ºC).",
    "maturacao": "3 meses em barricas de carvalho de segundo e terceiro usos.",
    "corpo": "Médio",
    "potencial_guarda_anos": "3 a 5 anos",
    "harmonizacoes": [
      "Carnes vermelhas assadas",
      "beringela parmeggiana",
      "queijo parmesão"
    ]
  },
  "midia": {
    "imagem_principal_url": "https://images.tcdn.com.br/img/img_prod/791130/sol_sul_malbec_tinto_225_1_4f7f901c8b252cec89f6c9e59aa3e41b_20221003162157.png",
    "ficha_tecnica_url": "https://drive.usercontent.google.com/u/2/uc?id=1GvQz7Cdwe3TKMNLu6kTVTPpTtClh7xaM&export=download"
  }
}