{
  "codigo_produto": "317",
  "url": "https://www.tdpwines.com.br/vinho-tinto-italiano-poggio-del-salici-chianti-docg",
  "titulo": "Poggio del Salici Chianti DOCG 2021",
  "descricao_geral": "Poggio del Salici é um inconfundível representante da região de Chianti, na Toscana, de onde saem alguns dos melhores vinhos italianos. O nome Poggio del Salici, que significa Colina dos Salgueiros, representa bem a imagem desta belíssima região, cheia de colinas, espaço aberto e árvores esparsas entremeadas por vinhedos.Sobretudo, um Chianti de grande tipicidade. Corte de 75% de Sangiovese e 25% de Canaiolo, em uma vinificação que dispensa passagem por madeira, o vinho tem excelente drinkability, ou seja, é fresco e fácil de beber.A fruta vermelha madura domina, com destaque para cerejas e ameixas, junto à nota floral e de ervas secas. Tem corpo médio, textura sedosa, taninos firmes, mas bem trabalhados, e boa acidez. CaracteristicasProdutor Terre CevicoPais ItáliaRegião ToscanaTipo TintoUva 75% Sangiovese, 25% CanaioloVolume 750mlSafra 2021Teor Alcoólico 13%Temperatura de Serviço 14°CVinificação Fermentação tradicional com temperatura controlada.Maturação Tanques de aço inoxCorpo MédioPotencial de Guarda 5 anosHarmonizações Carnes vermelhas magras na grelha, massa com molho de tomate, filé à parmegiana. Baixar Ficha Técnica Baixar Imagem",
  "caracteristicas": {
    "produtor": "Terre Cevico",
    "pais": "Ver País Argentina Patagonia Chile Portugal Brasil Espanha Ribera del Duero Itália Piemonte Abruzzo Sicilia Provincia de Taranto Toscana França África do Sul",
    "regiao": "Toscana",
    "tipo": "Tinto",
    "uva": "75% Sangiovese, 25% Canaiolo",
    "volume_ml": 750,
    "safra": "2021",
    "teor_alcoolico_percent": 13.0,
    "temperatura_servico_c": "14°C",
    "vinificacao": "Fermentação tradicional com temperatura controlada.",
    "maturacao": "Tanques de aço inox",
    "corpo": "Médio",
    "potencial_guarda_anos": "5 anos",
    "harmonizacoes": [
      "Carnes vermelhas magras na grelha",
      "massa com molho de tomate",
      "filé à parmegiana"
    ]
  },
  "midia": {
    "imagem_principal_url": "https://images.tcdn.com.br/img/img_prod/791130/poggio_del_salici_chianti_docg_2021_317_1_9b45436b7bca2c5b3b56dcff343e320f.png",
    "ficha_tecnica_url": "https://drive.usercontent.google.com/u/2/uc?id=1jV8CaDMc0nbLVr9ELHqnZu9rRN5WJG18&export=download"
  }
}