{
  "codigo_produto": "263",
  "url": "https://www.tdpwines.com.br/vinho-branco-espanhol-la-miranda-de-secastilla-garnacha-blanca",
  "titulo": "La Miranda de Secastilla Garnacha Blanca 2021",
  "descricao_geral": "91 pontos IWC90 pontos James Suckling90 pontos Guia PeñinA DO Somontano fica na província de Aragón, aos pés dos Pireneus, cadeia montanhosa que divide a Espanha da França. Os vinhedos de Secastilla ficam em um vale escondido, a cerca de 800 metros acima do nível do mar, onde, tradicionalmente, se cultiva a Garnacha. Não muito conhecida do público, se destaca por apresentar rótulos de excelente custo-benefício, que não raro valem muito mais do que custam.A Garnacha Blanca (ou Grenache Blanc) é originária do Norte da Espanha e origina vinhos brancos de aroma muito intenso, com notas de maçã verde e melão. Este exemplar, com suas vinhas de altitude, conserva excelente acidez e traz, além do já referido frutado, que se confirma no nariz e na boca, um toque mineral proveniente do terreno pobre e pedregoso do Vale de Secastilla.Com quatro meses de passagem por carvalho francês, com battonages frequentes, é companhia perfeita para frutos do mar, saladas de feijão branco com hortelã e massas com molhos brancos. CaracteristicasProdutor Viñas del VeroPais EspanhaRegião SomontanoTipo BrancoUva 100% Garnacha BlancaVolume 750mlSafra 2021Teor Alcoólico 13,5%Temperatura de Serviço 14°CVinificação Colheita manual. Fermentação com leveduras indígenas com temperatura controlada.Maturação 4 meses em barricas de carvalho francês com battonage.Corpo MédioPotencial de Guarda 5 anosHarmonizações Frutos do mar, massas com molhos brancos, carnes brancas grelhadas. Baixar Ficha Técnica Baixar Imagem",
  "caracteristicas": {
    "produtor": "Viñas del Vero",
    "pais": "Ver País Argentina Patagonia Chile Portugal Brasil Espanha Ribera del Duero Itália Piemonte Abruzzo Sicilia Provincia de Taranto Toscana França África do Sul",
    "regiao": "Somontano",
    "tipo": "Branco",
    "uva": "100% Garnacha Blanca",
    "volume_ml": 750,
    "safra": "2021",
    "teor_alcoolico_percent": 13.5,
    "temperatura_servico_c": "14°C",
    "vinificacao": "Colheita manual. Fermentação com leveduras indígenas com temperatura controlada.",
    "maturacao": "4 meses em barricas de carvalho francês com battonage.",
    "corpo": "Médio",
    "potencial_guarda_anos": "5 anos",
    "harmonizacoes": [
      "Frutos do mar",
      "massas com molhos brancos",
      "carnes brancas grelhadas"
    ]
  },
  "midia": {
    "imagem_principal_url": "https://images.tcdn.com.br/img/img_prod/791130/la_miranda_de_secastilla_garnacha_blanca_2019_263_1_fca4adc5128eedac8bd349256edea5a8_20221003162202.png",
    "ficha_tecnica_url": "https://drive.usercontent.google.com/u/2/uc?id=1G0tCqCp6-pcP6R52vSYr6EZgFRFHElvX&export=download"
  }
}