{
  "codigo_produto": "251",
  "url": "https://www.tdpwines.com.br/vinho-tinto-italiano-menhir-primitivo-di-manduria-doc",
  "titulo": "Menhir Salento Primitivo di Manduria DOC 2020",
  "descricao_geral": "92 pontos Luca MaroniA cantina Menhir Salento une o conhecimento de ontem com as possibilidades do amanhã. Respeitando a tradição, traz, com uma vinícola moderna e produção agrícola integrada, alguns dos vinhos mais interessantes da região de Lecce, no &#39;salto da bota&#39; italiana.A Primitivo é a uva mais conhecida da Puglia, e a DOC Manduria, uma das mais conceituadas. Voluptuoso, corpulento, este vinho agrada a quem procura vinhos muito típicos da uva e da zona. Com seis meses de passagem por barricas de carvalho francês, o aroma é predominantemente de notas doces como ameixa, geléia de cereja e tabaco. Em boca, é amplo, com muito corpo e taninos maduros e integrados.Assados de carne, como cordeiro, são os pratos mais indicados para serem harmonizados com este vinho. CaracteristicasProdutor Menhir SalentoPais ItáliaRegião ManduriaTipo TintoUva 100% PrimitivoVolume 750mlSafra 2020Teor Alcoólico 14,5%Temperatura de Serviço 16°CVinificação Colheita Manual. Fermentação tradicional com temperatura a 22-24ºC por 10 dias.Maturação 6 meses em barricas de carvalho francês e americano de segundo uso.Corpo EncorpadoPotencial de Guarda 10 anosHarmonizações Carne vermelha grelhada, carne de caça, queijos maturados. Baixar Ficha Técnica Baixar Imagem",
  "caracteristicas": {
    "produtor": "Menhir Salento",
    "pais": "Ver País Argentina Patagonia Chile Portugal Brasil Espanha Ribera del Duero Itália Piemonte Abruzzo Sicilia Provincia de Taranto Toscana França África do Sul",
    "regiao": "Manduria",
    "tipo": "Tinto",
    "uva": "100% Primitivo",
    "volume_ml": 750,
    "safra": "2020",
    "teor_alcoolico_percent": 14.5,
    "temperatura_servico_c": "16°C",
    "vinificacao": "Colheita Manual. Fermentação tradicional com temperatura a 22-24ºC por 10 dias.",
    "maturacao": "6 meses em barricas de carvalho francês e americano de segundo uso.",
    "corpo": "Encorpado",
    "potencial_guarda_anos": "10 anos",
    "harmonizacoes": [
      "Carne vermelha grelhada",
      "carne de caça",
      "queijos maturados"
    ]
  },
  "midia": {
    "imagem_principal_url": "https://images.tcdn.com.br/img/img_prod/791130/menhir_salento_primitivo_di_manduria_doc_2019_251_1_9f18ed0f6f3a2bfac86bc60d1b11023c_20221003162202.png",
    "ficha_tecnica_url": "https://drive.usercontent.google.com/u/2/uc?id=1jILPFPpLp4Z9NbB0T_0khbVAstsMNNPY&export=download"
  }
}