{
  "codigo_produto": "137",
  "url": "https://www.tdpwines.com.br/vinho-tinto-argentino-gen-del-alma-crua-chan-malbec",
  "titulo": "Gen del Alma Crua Chan Gualta Malbec 2017",
  "descricao_geral": "96 pontos Descorchados94 Pontos Robert ParkerCrua Chan Gualta Malbec é outro excelente vinho da Gen del Alma, projeto familiar iniciado em 2011 com um objetivo claro: trazer ao consumidor vinhos puros, com mínima intervenção enológica. Seus vinhedos estão localizados no solo calcário de Gualtallary, Vale do Uco, a 1400m de altitude, onde as videiras se esforçam bastante para retornarem rendimentos muito baixos.O Crua Chan é elaborado 100% com uvas Malbec desta zona, colhidas manualmente. A fermentação ocorre em grandes barris de carvalho neutro, com o uso de leveduras autóctones e 30% das uvas com o cacho inteiro. Após, o vinho segue para fermentação em barricas de carvalho francês de 500 litros, usadas, onde amadurece por 12 longos meses antes de ser engarrafado sem correções ou filtragens.O vinho tem uma estrutura invejável, que desponta já no nariz. Frutas vermelhas e negras, frescas e maduras são acompanhadas de toques de especiarias doces (canela), giz, cacau e uma grande gama de notas florais. Em boca, seus taninos diretos e secos fundem-se a uma acidez generosa, tornando-o perfeito para acompanhar grandes refeições à base de carne! CaracteristicasProdutor Gen Del AlmaPais ArgentinaRegião Vale de Tupungato, MendozaTipo TintoUva 100% MalbecVolume 750mlSafra 2017Teor Alcoólico 14%Temperatura de Serviço 14 a 16°CVinificação Fermentação em ânforas de concreto a baixa temperatura com 30% dos cachos inteiros.Maturação 12 meses em barricas de carvalho francês usadas de 500 litros.Corpo IntensoPotencial de Guarda 7 a 10 anosHarmonizações Carnes vermelhas assadas, queijos fortes. Baixar Ficha Técnica Baixar Imagem",
  "caracteristicas": {
    "produtor": "Gen Del Alma",
    "pais": "Ver País Argentina Patagonia Chile Portugal Brasil Espanha Ribera del Duero Itália Piemonte Abruzzo Sicilia Provincia de Taranto Toscana França África do Sul",
    "regiao": "Vale de Tupungato, Mendoza",
    "tipo": "Tinto",
    "uva": "100% Malbec",
    "volume_ml": 750,
    "safra": "2017",
    "teor_alcoolico_percent": 14.0,
    "temperatura_servico_c": "14 a 16°C",
    "vinificacao": "Fermentação em ânforas de concreto a baixa temperatura com 30% dos cachos inteiros.",
    "maturacao": "12 meses em barricas de carvalho francês usadas de 500 litros.",
    "corpo": "Intenso",
    "potencial_guarda_anos": "7 a 10 anos",
    "harmonizacoes": [
      "Carnes vermelhas assadas",
      "queijos fortes"
    ]
  },
  "midia": {
    "imagem_principal_url": "https://images.tcdn.com.br/img/img_prod/791130/gen_del_alma_crua_chan_gualta_malbec_2017_137_1_20221003162142.png",
    "ficha_tecnica_url": "https://drive.google.com/u/0/uc?id=13UclsOVLJdzdhYlIlFWYG6f19PMg1Acg&export=download"
  }
}