{
  "codigo_produto": "227",
  "url": "https://www.tdpwines.com.br/vinho-branco-argentino-sol-sul-torrontes",
  "titulo": "Sol Sul Torrontes Branco 2023",
  "descricao_geral": "O sol brilha mais ao sul do continente americano! Os vinhos da linha Sol Sul foram criados com muito cuidado pelo enólogo Tiago Dal Pizzol para expressarem as melhores características varietais de suas uvas, trazendo sempre varietais que são grandes clássicos do mundo do vinho.Este branco vem da área mais nobre e conhecida do país vizinho, Mendoza, e fielmente apresenta tudo o que se espera da uva branca mais plantada na Argentina, a Torrontés. Muito fresco, o vinho tem um delicioso aroma que une notas de floras brancas, frutas cítricas e tropicais e um leve toque mineral. Sem passagem por madeira e com a acidez refrescante como maior qualidade, a sensação em boca do vinho é muito agradável.Pronto para beber, este vinho é muito versátil na harmonização, podendo acompanhar pratos leves como saladas, peixes e frutos do mar. CaracteristicasProdutor TDP WinesPais ArgentinaRegião MendozaTipo BrancoUva 100% TorrontésVolume 750mlSafra 2023Teor Alcoólico 13%Temperatura de Serviço 8 a 10°CVinificação Vinificação tradicional em tanques com controle de temperatura.Maturação Em tanques de aço inoxCorpo LevePotencial de Guarda 3 anosHarmonizações Peixes, carnes brancas, saladas e frutos do mar. Baixar Ficha Técnica Baixar Imagem",
  "caracteristicas": {
    "produtor": "TDP Wines",
    "pais": "Ver País Argentina Patagonia Chile Portugal Brasil Espanha Ribera del Duero Itália Piemonte Abruzzo Sicilia Provincia de Taranto Toscana França África do Sul",
    "regiao": "Mendoza",
    "tipo": "Branco",
    "uva": "100% Torrontés",
    "volume_ml": 750,
    "safra": "2023",
    "teor_alcoolico_percent": 13.0,
    "temperatura_servico_c": "8 a 10°C",
    "vinificacao": "Vinificação tradicional em tanques com controle de temperatura.",
    "maturacao": "Em tanques de aço inox",
    "corpo": "Leve",
    "potencial_guarda_anos": "3 anos",
    "harmonizacoes": [
      "Peixes",
      "carnes brancas",
      "saladas",
      "frutos do mar"
    ]
  },
  "midia": {
    "imagem_principal_url": "https://images.tcdn.com.br/img/img_prod/791130/sol_sul_torrontes_branco_227_1_ef46c9e856e3a49a3f8eaff7e20274e9_20221003162153.png",
    "ficha_tecnica_url": "https://drive.usercontent.google.com/u/2/uc?id=1GpWTKjWgvSkDug3vBJ14V_xje3evqSxC&export=download"
  }
}