{
  "codigo_produto": "391",
  "url": "https://www.tdpwines.com.br/vinho-tinto-chileno-veramonte-gran-reserva-merlot",
  "titulo": "Veramonte Gran Reserva Merlot 2022",
  "descricao_geral": "Um aveludado e intenso Merlot de Casablanca, com notas de mirtilo, groselha e especiarias, junto a notas tostadas da madeira. Certificadamente orgânico. CaracteristicasProdutor VeramontePais ChileRegião CasablancaTipo TintoUva 100% MerlotVolume 750mlSafra 2022Teor Alcoólico 14%Temperatura de Serviço 14 a 16°CVinificação Maceração a frio por 5 dias, fermentação com leveduras nativas. Maceração pósfermentativa por 10 dias.Maturação 12 meses em barricas de carvalho francês.Corpo MédioPotencial de Guarda 5 anosHarmonizações Carne vermelha grelhada, coxa e sobrecoxa de frango, massas recheadas, queijo de massa média. Baixar Ficha Técnica Baixar Imagem",
  "caracteristicas": {
    "produtor": "Veramonte",
    "pais": "Ver País Argentina Patagonia Chile Portugal Brasil Espanha Ribera del Duero Itália Piemonte Abruzzo Sicilia Provincia de Taranto Toscana França África do Sul",
    "regiao": "Casablanca",
    "tipo": "Tinto",
    "uva": "100% Merlot",
    "volume_ml": 750,
    "safra": "2022",
    "teor_alcoolico_percent": 14.0,
    "temperatura_servico_c": "14 a 16°C",
    "vinificacao": "Maceração a frio por 5 dias, fermentação com leveduras nativas. Maceração pósfermentativa por 10 dias.",
    "maturacao": "12 meses em barricas de carvalho francês.",
    "corpo": "Médio",
    "potencial_guarda_anos": "5 anos",
    "harmonizacoes": [
      "Carne vermelha grelhada",
      "coxa",
      "sobrecoxa de frango",
      "massas recheadas",
      "queijo de massa média"
    ]
  },
  "midia": {
    "imagem_principal_url": "https://images.tcdn.com.br/img/img_prod/791130/veramonte_gran_reserva_merlot_2022_391_1_7270d6da03c15f22ff74c34e8852d47e.png",
    "ficha_tecnica_url": "https://drive.usercontent.google.com/uc?id=1KLElq3AO6G9QgHyHAV5qHOPr8glSC7Pt&export=download"
  }
}