{
  "codigo_produto": "309",
  "url": "https://www.tdpwines.com.br/vinho-tinto-argentino-finca-la-anita-syrah",
  "titulo": "Vinho Tinto Finca La Anita Syrah 750ml 2021",
  "descricao_geral": "Finca La Anita é uma das mais tradicionais bodegas de Mendoza e a primeira a se estabelecer em Alto Agrelo, na famosa Calle Cobos, local onde hoje estão as grandes marcas do vinho argentino como Catena Zapata e Cobos, entre outras. Este Syrah utiliza as vinhas mais antigas da propriedade, com 85 anos, plantadas pelo proprietário anterior e conduzidas em pérgola trentina.Um Syrah muito característico, carnoso, com notas de frutas maduras como cassis e mirtilos, além de notas de especiarias e de baunilha. Em boca, é cheio, robusto, com um final muito longo que o torna incrivelmente versátil nas harmonizações.Harmoniza com carnes vermelhas assadas, risoto de cogumelos, massas pesadas, como à Putanesca. CaracteristicasProdutor Finca La AnitaPais ArgentinaRegião Agrelo, MendozaTipo TintoUva 100% SyrahVolume 750mlSafra 2021Teor Alcoólico 13,5%Temperatura de Serviço 16°CVinificação Fermentação em tanques de inox com leveduras selecionadas. Fermentação malolática espontânea com controle de temperatura.Maturação 12 meses em barricas francesas e americanas novas e de um ano de uso. Tosta média.Corpo EncorpadoPotencial de Guarda 7 anosHarmonizações Risoto de cogumelos, strogonoff, massa à putanesca, carne vermelha grelhada. Baixar Ficha Técnica Baixar Imagem",
  "caracteristicas": {
    "produtor": "Finca La Anita",
    "pais": "Ver País Argentina Patagonia Chile Portugal Brasil Espanha Ribera del Duero Itália Piemonte Abruzzo Sicilia Provincia de Taranto Toscana França África do Sul",
    "regiao": "Agrelo, Mendoza",
    "tipo": "Tinto",
    "uva": "100% Syrah",
    "volume_ml": 750,
    "safra": "2021",
    "teor_alcoolico_percent": 13.5,
    "temperatura_servico_c": "16°C",
    "vinificacao": "Fermentação em tanques de inox com leveduras selecionadas. Fermentação malolática espontânea com controle de temperatura.",
    "maturacao": "12 meses em barricas francesas e americanas novas e de um ano de uso. Tosta média.",
    "corpo": "Encorpado",
    "potencial_guarda_anos": "7 anos",
    "harmonizacoes": [
      "com carnes vermelhas assadas",
      "risoto de cogumelos",
      "massas pesadas",
      "como à Putanesca"
    ]
  },
  "midia": {
    "imagem_principal_url": "https://images.tcdn.com.br/img/img_prod/791130/vinho_tinto_finca_la_anita_syrah_750ml_309_1_bc9ed7f546560d462a33fca5edcd66b9_20221003162152.png",
    "ficha_tecnica_url": "https://drive.usercontent.google.com/u/2/uc?id=1EkDf3ibcjU4u5MlKKsqg1o9A7NWRcn0x&export=download"
  }
}