{
  "codigo_produto": "325",
  "url": "https://www.tdpwines.com.br/vinho-tinto-argentino-tapiz-seleccion-de-barricas-blend",
  "titulo": "Vinho Tinto Argentino Tapiz Seleccion De Barricas Blend 2018",
  "descricao_geral": "Cor púrpura profunda, com muita intensidade aromática, especialmente notas de frutas vermelhas e negras, junto a café torrado e chocolate negro. Taninos maduros e macios, muita intensidade e persistência em boca. CaracteristicasProdutor TapizPais ArgentinaRegião San Pablo, MendozaTipo TintoUva Malbec (40%), Cabernet Sauvignon (25%), Merlot (20%), Cabernet Franc (10%), Syrah (5%)Volume 750mlSafra 2018Teor Alcoólico 14,4%Temperatura de Serviço 16°CVinificação Maceração pré-fermentativa a frio por 5 a 8 dias. Fermentação tradicional em tanques de aço inox a 28ºC por 10 a 14 dias.Maturação 18 meses em barricas de carvalho francês novo mais 12 meses em garrafa.Corpo IntensoPotencial de Guarda 10 anosHarmonizações Carnes vermelhas grelhadas e de longo cozimento. Baixar Ficha Técnica Baixar Imagem",
  "caracteristicas": {
    "produtor": "Tapiz",
    "pais": "Ver País Argentina Patagonia Chile Portugal Brasil Espanha Ribera del Duero Itália Piemonte Abruzzo Sicilia Provincia de Taranto Toscana França África do Sul",
    "regiao": "San Pablo, Mendoza",
    "tipo": "Tinto",
    "uva": "Malbec (40%), Cabernet Sauvignon (25%), Merlot (20%), Cabernet Franc (10%), Syrah (5%)",
    "volume_ml": 750,
    "safra": "2018",
    "teor_alcoolico_percent": 14.4,
    "temperatura_servico_c": "16°C",
    "vinificacao": "Maceração pré-fermentativa a frio por 5 a 8 dias. Fermentação tradicional em tanques de aço inox a 28ºC por 10 a 14 dias.",
    "maturacao": "18 meses em barricas de carvalho francês novo mais 12 meses em garrafa.",
    "corpo": "Intenso",
    "potencial_guarda_anos": "10 anos",
    "harmonizacoes": [
      "Carnes vermelhas grelhadas",
      "de longo cozimento"
    ]
  },
  "midia": {
    "imagem_principal_url": "https://images.tcdn.com.br/img/img_prod/791130/vin_arg_tapiz_seleccion_de_barricas_blend_tto_6_x_750_ml_325_1_ea6c94274889d5104809f42d559c26a9.png",
    "ficha_tecnica_url": "https://drive.usercontent.google.com/u/2/uc?id=1IGjsyqZCxR7O86gDIZ1vLSwDkBjADrsy&export=download"
  }
}