{
  "codigo_produto": "215",
  "url": "https://www.tdpwines.com.br/vinho-tinto-chileno-ola-po-merlot",
  "titulo": "Ola Po Merlot Tinto 2021",
  "descricao_geral": "Ola, poh! No Chile, o 'poh' é uma verdadeira insitituição nacional, uma gíria que faz parte do cotidiano do país. No Brasil, seria o equivalente ao 'bah' dos gaúchos, o 'oxe' dos baianos ou o infalível 'uai' mineiro. Ola poh, mais que tudo, é um convite a experimentar um vinho incrível!100% Merlot, este tinto de ótima tipicidade é elaborado no vale de Curicó, mais especialmente em Peñaflor, no coração do vale, onde as condições são muito boas para a produção de tintos de ótimo equilíbrio e complexidade. Sem passagem por madeira, o foco é na expressão da fruta, e o que encontramos neste vinho é um aroma intenso, de um delicioso frutado, com notas de ameixa e mirtilo. Com uma estrutura bem redonda, marcada por seus taninos macios e acidez equilibrada, é muito fácil de beber e de gostar!Olapo Merlot é perfeito para ser bebido só ou acompanhado carnes grelhadas e pratos do dia-a-dia. CaracteristicasProdutor TDP WinesPais ChileRegião Valle de CuricóTipo TintoUva 100% MerlotVolume 750mlSafra 2021Teor Alcoólico 13%Temperatura de Serviço 12 a 14°CVinificação Vinificação tradicional em tanques com controle de temperaturaMaturação Tanques de aço inoxCorpo MédioPotencial de Guarda 3 a 5 anosHarmonizações Carnes vermelhas grelhadas, queijos de massa média Baixar Ficha Técnica Baixar Imagem",
  "caracteristicas": {
    "produtor": "TDP Wines",
    "pais": "Ver País Argentina Patagonia Chile Portugal Brasil Espanha Ribera del Duero Itália Piemonte Abruzzo Sicilia Provincia de Taranto Toscana França África do Sul",
    "regiao": "Valle de Curicó",
    "tipo": "Tinto",
    "uva": "100% Merlot",
    "volume_ml": 750,
    "safra": "2021",
    "teor_alcoolico_percent": 13.0,
    "temperatura_servico_c": "12 a 14°C",
    "vinificacao": "Vinificação tradicional em tanques com controle de temperatura",
    "maturacao": "Tanques de aço inox",
    "corpo": "Médio",
    "potencial_guarda_anos": "3 a 5 anos",
    "harmonizacoes": [
      "Carnes vermelhas grelhadas",
      "queijos de massa média"
    ]
  },
  "midia": {
    "imagem_principal_url": "https://images.tcdn.com.br/img/img_prod/791130/ola_po_merlot_tinto_2021_215_1_1dfbe33a32b49686c8c587c0f92ad8b3.png",
    "ficha_tecnica_url": "https://drive.usercontent.google.com/u/2/uc?id=1Fl1PvS3r2z41ylh7NUNPBH0cWBJj-ktK&export=download"
  }
}