{
  "codigo_produto": "207",
  "url": "https://www.tdpwines.com.br/vinho-tinto-argentino-tapiz-vso-malbec",
  "titulo": "Tapiz VSO Malbec Orgânico 2019",
  "descricao_geral": "VSO - Vino Sostenible Organico, ou Vinho Sustentável Orgânico - é um vinho Malbec orgânico elaborado pela Tapiz, uma das bodegas argentinas mais atentas ao detalhe. A marca, originalmente pertencente a um grupo californiano, foi comprada em 2003 pela família Ortiz, que, desde então, tem se ocupado em oferecer grandes experiências por meio de excelentes vinhos. Com a maioria de seus vinhedos na zona de Tupungato, em Mendoza, conta desde 2012 com a consultoria exclusiva do enólogo Jean Claude Berrouet, que por mais de quarenta anos foi responsável pela elaboração dos lendários vinhos de Chateau Petrus em Bordeaux.VSO é elaborado com uvas orgânicas do vinhedo com o sugestivo nome de Finca Las Uvas, na zona de Tupungato, no Vale do Uco. Além das uvas, todos os insumos utilizados, até mesmo as leveduras, são certificadas orgânicas.Com oito meses em passagem por barricas de carvalho novas, VSO Malbec tem notas de frutas vermelhas frescas, como morango, amoras e ameixas, junto à baunilha oriunda da barrica. Em boca, é equilibrado, vivaz e elegante. CaracteristicasProdutor TapizPais ArgentinaRegião Tupungato, MendozaTipo TintoUva 100% MalbecVolume 750mlSafra 2019Teor Alcoólico 14%Temperatura de Serviço 14 a 16°CVinificação Pré-maceração a frio por 5 a 8 dias. Fermentação tradicional em tanques de aço inox a 28ºC por 10 a 14 dias. Leveduras selecionadas.Maturação 8 meses em barricas de carvalho.Corpo MédioPotencial de Guarda 5 anosHarmonizações Carnes vermelhas grelhadas, como entrecot, lasanha de beringela, queijos como o Gouda. Baixar Ficha Técnica Baixar Imagem",
  "caracteristicas": {
    "produtor": "Tapiz",
    "pais": "Ver País Argentina Patagonia Chile Portugal Brasil Espanha Ribera del Duero Itália Piemonte Abruzzo Sicilia Provincia de Taranto Toscana França África do Sul",
    "regiao": "Tupungato, Mendoza",
    "tipo": "Tinto",
    "uva": "100% Malbec",
    "volume_ml": 750,
    "safra": "2019",
    "teor_alcoolico_percent": 14.0,
    "temperatura_servico_c": "14 a 16°C",
    "vinificacao": "Pré-maceração a frio por 5 a 8 dias. Fermentação tradicional em tanques de aço inox a 28ºC por 10 a 14 dias. Leveduras selecionadas.",
    "maturacao": "8 meses em barricas de carvalho.",
    "corpo": "Médio",
    "potencial_guarda_anos": "5 anos",
    "harmonizacoes": [
      "Carnes vermelhas grelhadas",
      "como entrecot",
      "lasanha de beringela",
      "queijos como o Gouda"
    ]
  },
  "midia": {
    "imagem_principal_url": "https://images.tcdn.com.br/img/img_prod/791130/tapiz_vso_malbec_organico_2019_207_1_5dea2ca040821e941059153f3cea98e3_20221003162147.png",
    "ficha_tecnica_url": "https://drive.usercontent.google.com/u/2/uc?id=1Hs3Lqmx8w8X2WAFC4YyjpqgyQGxKEFtT&export=download"
  }
}