{
  "codigo_produto": "269",
  "url": "https://www.tdpwines.com.br/vinho-tinto-chileno-nobs-cabernet-sauvignon",
  "titulo": "NOBS Cabernet Sauvignon 2021",
  "descricao_geral": "NOBS? No bull shit, apenas vinho! NOBS é um convite simples, direto, para aproveitar o seu vinho, sem ressalvas, sem julgamentos, sem arrependimentos!O vinho reflete seu rótulo. Direto e certeiro, este Cabernet Sauvignon 100%, com três meses de passagem por barrica, é elaborado no vale de Curicó, na zona de Rauco, reconhecida internacionalmente pela potência e tipicidade de seus Cabernet Sauvignon e Carménère. Com notas de frutas vermelhas maduras, como cereja e cassis, e também de tabaco e chocolate, tem uma excelente sensação de boca, com taninos presentes, mas macios, e corpo médio, junto a uma gastronômica acidez.NOBS Cabernet Sauvignon é perfeito para ser consumido com pratos à base de carne vermelha, especialmente assada, como num bom churrasco, sem nada mais. NOBS! CaracteristicasProdutor TDP WinesPais ChileRegião Valle de CuricóTipo TintoUva 100% Cabernet SauvignonVolume 750mlSafra 2021Teor Alcoólico 13%Temperatura de Serviço 14°CVinificação Vinificação tradicional em tanques com controle de temperaturaMaturação 3 meses em barricas de carvalho de segundo e terceiro usosCorpo MédioPotencial de Guarda 3 a 5 anosHarmonizações Carnes vermelhas grelhadas, queijos de massa média Baixar Ficha Técnica Baixar Imagem",
  "caracteristicas": {
    "produtor": "TDP Wines",
    "pais": "Ver País Argentina Patagonia Chile Portugal Brasil Espanha Ribera del Duero Itália Piemonte Abruzzo Sicilia Provincia de Taranto Toscana França África do Sul",
    "regiao": "Valle de Curicó",
    "tipo": "Tinto",
    "uva": "100% Cabernet Sauvignon",
    "volume_ml": 750,
    "safra": "2021",
    "teor_alcoolico_percent": 13.0,
    "temperatura_servico_c": "14°C",
    "vinificacao": "Vinificação tradicional em tanques com controle de temperatura",
    "maturacao": "3 meses em barricas de carvalho de segundo e terceiro usos",
    "corpo": "Médio",
    "potencial_guarda_anos": "3 a 5 anos",
    "harmonizacoes": [
      "Carnes vermelhas grelhadas",
      "queijos de massa média"
    ]
  },
  "midia": {
    "imagem_principal_url": "https://images.tcdn.com.br/img/img_prod/791130/nobs_cabernet_sauvignon_2020_269_1_e410be497260853d41532d891ae70fd5_20221003162142.png",
    "ficha_tecnica_url": "https://drive.usercontent.google.com/u/2/uc?id=1Fo67BYr9cm_ieN2ZC4QO58ibEpeYeJnj&export=download"
  }
}