{
  "codigo_produto": "223",
  "url": "https://www.tdpwines.com.br/vinho-tinto-portugues-regateiro-junior-bairrada",
  "titulo": "Regateiro Jr Tinto Bairrada DOC 2018",
  "descricao_geral": "Regateiro é, dentro da Lusovini, um projeto na Bairrada capitaneado por um de seus sócio-fundadores, Casimiro Gomes em homenagem a seu avô Manuel Gomes Regateiro Júnior. Manuel, que residia em Aguada de Cima, transformou os solos argilosos em azulejos tradicionais e também em parreirais, dando origem a vinhos que contam e fazem parte da identidade da Bairrada, elaborados principalmente com a casta Baga. Em nome de uma relação familiar com o vinho de mais de 350 anos, Casimiro continua o legado do seu avô com os vinhos do projeto Regateiro.Regateiro Jr Bairrada DOC marca a entrada do filho de Casimiro, Carlos, no projeto. Este tinto leva, além da tradicional Baga, as Tintas Pinheira, Roriz e Amarela e a Touriga Nacional. Não passa por madeira, tendo Carlos e Casimiro optado por expressar um frescor e fruta superiores. De longa maceração, é vinho de uma belíssima cor rubi e que tem um aroma muito destacado, com um conjunto exuberante de fruta vermelha madura e ligeiramente compotada e notas de torrefação e especiarias. Em boca, tem corpo médio, é seco e tem taninos elegantes mas firmes, presentes. Tem ótimo final de boca, e a sensação de frescor pede pela próxima taça.Regateiro Jr Tinto é perfeito para ser consumido com pratos típicos da Bairrada, como o leitão assado, além de molhos vermelhos mais encorpados e embutidos. CaracteristicasProdutor LusoviniPais PortugalRegião BairradaTipo TintoUva Tinta Pinheira, Tinta Amarela, Touriga Nacional, Baga e Tinta RorizVolume 750mlSafra 2018Teor Alcoólico 13%Temperatura de Serviço 14 a 16°CVinificação Fermentação com longa maceração em temperatura controlada entre 24 e 26ºC.Maturação Em inox, com estágio em cave.Corpo MédioPotencial de Guarda 6 anosHarmonizações Carnes Grelhadas, assados, embutidos e queijos duros. Baixar Ficha Técnica Baixar Imagem",
  "caracteristicas": {
    "produtor": "Lusovini",
    "pais": "Ver País Argentina Patagonia Chile Portugal Brasil Espanha Ribera del Duero Itália Piemonte Abruzzo Sicilia Provincia de Taranto Toscana França África do Sul",
    "regiao": "Bairrada",
    "tipo": "Tinto",
    "uva": "Tinta Pinheira, Tinta Amarela, Touriga Nacional, Baga e Tinta Roriz",
    "volume_ml": 750,
    "safra": "2018",
    "teor_alcoolico_percent": 13.0,
    "temperatura_servico_c": "14 a 16°C",
    "vinificacao": "Fermentação com longa maceração em temperatura controlada entre 24 e 26ºC.",
    "maturacao": "Em inox, com estágio em cave.",
    "corpo": "Médio",
    "potencial_guarda_anos": "6 anos",
    "harmonizacoes": [
      "Carnes Grelhadas",
      "assados",
      "embutidos",
      "queijos duros"
    ]
  },
  "midia": {
    "imagem_principal_url": "https://images.tcdn.com.br/img/img_prod/791130/regateiro_jr_tinto_bairrada_doc_2018_223_1_49f144294674db78c252834ad7f1d209.jpg",
    "ficha_tecnica_url": "https://drive.usercontent.google.com/u/2/uc?id=1NLVSn87A6Rog04liBqtUhZc-afzJPx5g&export=download"
  }
}