{
  "codigo_produto": "241",
  "url": "https://www.tdpwines.com.br/vinho-branco-espanhol-oh-sister",
  "titulo": "De Andres Sisters Oh! Sister Verdejo Branco 2022",
  "descricao_geral": "As irmãs Ruth e Ana de Andres têm, com o vinho, uma relação muito bem resolvida. Inquietas, buscam, nos diversos terroirs espanhóis, criar vinhos inspiradores, que surgem após pesquisas, conversas, viagens e muita experimentação.Este branco de Rueda, na região de Castilla y León, é elaborado unicamente com a variedade Verdejo, que encontra sua melhor expressão justamente neste terreno. As uvas são colhidas à noite, com as temperaturas mais frescas auxiliando na retenção de acidez e aromas. O vinho é muito rico e aromático, com notas de frutas de caroço como pêssegos e damascos junto a um toque de louro e abacaxi. Em boca, tem corpo médio e se destaca pela acidez enérgica e vibrante.Sem passagem por madeira, este fresco Verdejo é companhia perfeita para peixes grelhados na manteiga, camarões, lulas e frutos do mar em geral. CaracteristicasProdutor De Andres SistersPais EspanhaRegião Rueda, Castilla y LeónTipo BrancoUva 100% VerdejoVolume 750mlSafra 2022Teor Alcoólico 12,5%Temperatura de Serviço 8°CVinificação Colheita noturna. Fermentação a temperatura controlada de 12ºC.Maturação Tanques de aço inoxCorpo LevePotencial de Guarda 3 a 5 anosHarmonizações Peixes, saladas e frutos do mar Baixar Ficha Técnica Baixar Imagem",
  "caracteristicas": {
    "produtor": "De Andres Sisters",
    "pais": "Ver País Argentina Patagonia Chile Portugal Brasil Espanha Ribera del Duero Itália Piemonte Abruzzo Sicilia Provincia de Taranto Toscana França África do Sul",
    "regiao": "Rueda, Castilla y León",
    "tipo": "Branco",
    "uva": "100% Verdejo",
    "volume_ml": 750,
    "safra": "2022",
    "teor_alcoolico_percent": 12.5,
    "temperatura_servico_c": "8°C",
    "vinificacao": "Colheita noturna. Fermentação a temperatura controlada de 12ºC.",
    "maturacao": "Tanques de aço inox",
    "corpo": "Leve",
    "potencial_guarda_anos": "3 a 5 anos",
    "harmonizacoes": [
      "Peixes",
      "saladas",
      "frutos do mar"
    ]
  },
  "midia": {
    "imagem_principal_url": "https://images.tcdn.com.br/img/img_prod/791130/de_andres_sisters_oh_sister_verdejo_branco_2020_241_1_91b32d0c94b3a397cd7ffc4bf2fe69e0_20221003162201.png",
    "ficha_tecnica_url": "https://drive.usercontent.google.com/u/2/uc?id=1H9gHPwnH8NIAhe5sK79EQxAY-mjwUewI&export=download"
  }
}