{
  "codigo_produto": "237",
  "url": "https://www.tdpwines.com.br/vinho-branco-portugues-pedra-cancela-intemporal",
  "titulo": "Pedra Cancela Intemporal Branco 2014",
  "descricao_geral": "Em seu aniversário de 20 anos, em 2020, Lusovini e Pedra Cancela apresentaram a primeira edição do Intemporal, um ousado lançamento comemorativo de um vinho branco já com oito anos de idade, sendo sete em cave. A proposta principal do vinho, segundo os enólogos João Paulo e Sónia Martins, foi provar, além da qualidade, o grande potencial de envelhecimento dos vinhos do Dão. Foi um sucesso estrondoso, com as 1200 garrafas lançadas terminando quase que imediatamente.Desde o ano 2000, a Pedra Cancela consolidou-se como um dos mais importantes projetos vinícolas do Dão. Desde o início, a proposta do enólogo João Paulo Gouveia foi unir modernidade e tradição, respeitando castas e saberes regionais sem perder de vista técnicas e estilos mais modernos.Esta nova edição, da safra 2014, segue o sucesso da primeira. De suas 1900 garrafas numeradas, pouco mais de sessenta estão no Brasil. 100% Encruzado, apresenta notas terciárias de mel e frutos secos, muito bem resolvidas com excelente toque mineral. Sem passagem por madeira, o vinho permanece por quatro meses em tanques de inox com suas borras finas. Em boca, se mostra complexo, volumoso e persistente, ainda muito vivo. Não é um branco de verão: a temperatura de consumo sugerida é de 12 graus, para melhor se notarem os aromas e sua complexidade. Antes de ser liberado, passou seis anos nas caves subterrâneas da Lusovini em Nelas, no Dão.É um vinho muito gastronômico, perfeito para ser consumido com os pratos tradicionais da gastronomia do Dão, como o queijo da Serra da Estrela e pratos de forno que levem batatas em seu preparo, como Bacalhau à Gomes de Sá e Polvo à Lagareiro. CaracteristicasProdutor LusoviniPais PortugalRegião DãoTipo BrancoUva EncruzadoVolume 750mlSafra 2014Teor Alcoólico 13,5%Temperatura de Serviço 12 a 14°CVinificação Desengace total, fermentação a baixas temperaturas.Maturação Quatro meses em tanques de inox, em contato com as borras finas.Corpo IntensoPotencial de Guarda 15 a 20 anosHarmonizações Polvo à lagareiro, bacalhau à Gomes de Sá, queijo da Serra da Estrela. Baixar Ficha Técnica Baixar Imagem",
  "caracteristicas": {
    "produtor": "Lusovini",
    "pais": "Ver País Argentina Patagonia Chile Portugal Brasil Espanha Ribera del Duero Itália Piemonte Abruzzo Sicilia Provincia de Taranto Toscana França África do Sul",
    "regiao": "Dão",
    "tipo": "Branco",
    "uva": "Encruzado",
    "volume_ml": 750,
    "safra": "2014",
    "teor_alcoolico_percent": 13.5,
    "temperatura_servico_c": "12 a 14°C",
    "vinificacao": "Desengace total, fermentação a baixas temperaturas.",
    "maturacao": "Quatro meses em tanques de inox, em contato com as borras finas.",
    "corpo": "Intenso",
    "potencial_guarda_anos": "15 a 20 anos",
    "harmonizacoes": [
      "Polvo à lagareiro",
      "bacalhau à Gomes de Sá",
      "queijo da Serra da Estrela"
    ]
  },
  "midia": {
    "imagem_principal_url": "https://images.tcdn.com.br/img/img_prod/791130/pedra_cancela_intemporal_branco_237_1_bcf80da995e2ad03ed381905520f6dfd_20221003162153.png",
    "ficha_tecnica_url": "https://drive.usercontent.google.com/u/2/uc?id=1Lbi3YSestpdg7ijqDLW8jmv2_ETK1LoZ&export=download"
  }
}