{
  "codigo_produto": "249",
  "url": "https://www.tdpwines.com.br/vinho-tinto-italiano-menhir-quota-29-primitivo-igt-salento",
  "titulo": "Menhir Salento Quota 29 Primitivo di Salento IGT 2021",
  "descricao_geral": "A cantina Menhir Salento une o conhecimento de ontem com as possibilidades do amanhã. Respeitando a tradição, traz, com uma vinícola moderna e produção agrícola integrada, alguns dos vinhos mais interessantes da região de Lecce, no ?salto da bota? italiana.Este tinto elaborado com a uva Primitivo não passa por madeira, mantendo toda a característica de fruta da variedade. No nariz, a fruta, portanto, domina, com notas de amarena, cereja, ameixa junto a um toque de chocolate meio-amargo e pimenta preta. Em boca, é redondo, quente, com uma estrutura muito sólida acompanhada de uma acidez que o equilibra.Carnes grelhadas, caça de pluma e queijos curados são ótimas companhias para este Primitivo. CaracteristicasProdutor Menhir SalentoPais ItáliaRegião SalentoTipo TintoUva 100% PrimitivoVolume 750mlSafra 2021Teor Alcoólico 14%Temperatura de Serviço 16°CVinificação Colheita Manual. Fermentação tradicional com temperatura a 22-24ºC por 10 dias.Maturação Tanques de aço inoxCorpo EncorpadoPotencial de Guarda 7 anosHarmonizações Carne vermelha grelhada, carne de caça, queijos maturados. Baixar Ficha Técnica Baixar Imagem",
  "caracteristicas": {
    "produtor": "Menhir Salento",
    "pais": "Ver País Argentina Patagonia Chile Portugal Brasil Espanha Ribera del Duero Itália Piemonte Abruzzo Sicilia Provincia de Taranto Toscana França África do Sul",
    "regiao": "Salento",
    "tipo": "Tinto",
    "uva": "100% Primitivo",
    "volume_ml": 750,
    "safra": "2021",
    "teor_alcoolico_percent": 14.0,
    "temperatura_servico_c": "16°C",
    "vinificacao": "Colheita Manual. Fermentação tradicional com temperatura a 22-24ºC por 10 dias.",
    "maturacao": "Tanques de aço inox",
    "corpo": "Encorpado",
    "potencial_guarda_anos": "7 anos",
    "harmonizacoes": [
      "Carne vermelha grelhada",
      "carne de caça",
      "queijos maturados"
    ]
  },
  "midia": {
    "imagem_principal_url": "https://images.tcdn.com.br/img/img_prod/791130/menhir_salento_quota_29_primitivo_di_salento_igt_2020_249_1_d33306099808d4f657c9523ea3721e48_20221003162202.png",
    "ficha_tecnica_url": "https://drive.usercontent.google.com/u/2/uc?id=1jM8LdQp8A3e-wFtxRt4nJkfA4HKeD5VE&export=download"
  }
}