{
  "codigo_produto": "415",
  "url": "https://www.tdpwines.com.br/vinhos/tinto/vinho-tinto-finca-de-finca-la-anita-cabernet-sauvignon",
  "titulo": "Vinho Tinto Finca de Finca La Anita Cabernet Sauvignon 2021",
  "descricao_geral": "Cabernet Sauvignon elaborado a 1100m de altitude. Cor rubi intensa, notas de cereja e amora com um toque de baunilha. Equilibrado, de longo final e boa acidez. CaracteristicasProdutor Finca La AnitaPais ArgentinaRegião Agrelo, MendozaTipo TintoUva 100% MalbecVolume 750mlSafra 2021Teor Alcoólico 14,5%Temperatura de Serviço 16°CVinificação Fermentação em tanques de inox com leveduras selecionadas. Fermentação malolática espontânea com controle de temperatura.Maturação 12 meses em barricas francesas e americanas.Corpo EncorpadoPotencial de Guarda 7 anosHarmonizações Picanha grelhada com pimenta preta, carnes vermelhas com chimichurri ou molhos condimentados. Baixar Ficha Técnica Baixar Imagem",
  "caracteristicas": {
    "produtor": "Finca La Anita",
    "pais": "Ver País Argentina Patagonia Chile Portugal Brasil Espanha Ribera del Duero Itália Piemonte Abruzzo Sicilia Provincia de Taranto Toscana França África do Sul",
    "regiao": "Agrelo, Mendoza",
    "tipo": "Tinto",
    "uva": "100% Malbec",
    "volume_ml": 750,
    "safra": "2021",
    "teor_alcoolico_percent": 14.5,
    "temperatura_servico_c": "16°C",
    "vinificacao": "Fermentação em tanques de inox com leveduras selecionadas. Fermentação malolática espontânea com controle de temperatura.",
    "maturacao": "12 meses em barricas francesas e americanas.",
    "corpo": "Encorpado",
    "potencial_guarda_anos": "7 anos",
    "harmonizacoes": [
      "Picanha grelhada com pimenta preta",
      "carnes vermelhas com chimichurri ou molhos condimentados"
    ]
  },
  "midia": {
    "imagem_principal_url": "https://images.tcdn.com.br/img/img_prod/791130/vinho_tinto_finca_de_finca_la_anita_cabernet_sauvignon_415_1_06e63ff9d1e72589f1a819d3ec6ebb81.jpg",
    "ficha_tecnica_url": "https://drive.usercontent.google.com/u/2/uc?id=1bBvUmLxrfPYOOBVOT2FjNI2pTYpaLoQU&export=download"
  }
}