{
  "codigo_produto": "377",
  "url": "https://www.tdpwines.com.br/vinho-tinto-organico-argentino-deriva-malbec-cruz-de-piedra",
  "titulo": "Vinho Orgânico Tinto Argentino Deriva Malbec Cruz de Piedra 2022",
  "descricao_geral": "Certificadamente orgânico, este Malbec traz um estilo cada vez mais valorizado por grande parte dos consumidores: um Malbec mais fresco e versátil, mais fácil de beber mas sem perder as características que o fazem um dos varietais favoritos dos brasileiros.É um vinho tinto de cor púrpura, profunda, e aromas concentrados de fruta negra, como ameixa, amora, cereja e um toque notável de violeta. Em boca, confirma as frutas no nariz junto a taninos macios. Em suma, é um vinho muito redondo.Fica perfeito para acompanhar pratos à base de carne vermelha e legumes.Seu produtor, a bodega Cruz de Piedra, tem mais de cinquenta anos de história na mais tradicional zona produtora argentina, Mendoza. Localizada em na zona de mesmo nome, Cruz de Piedra, dentro da chamada Primeira Zona, aos pés da Cordilheira dos Andes, na área de Maipú, a vinícola inspirou-se, em seu início, nos vinhos americanos da Califórnia, especialmente nos varietais elaborados 100% com uma única variedade. CaracteristicasProdutor Bodega Cruz de PiedraPais ArgentinaRegião Agrelo, MendozaTipo TintoUva 100% MalbecVolume 750mlSafra 2022Teor Alcoólico 13,5%Temperatura de Serviço 16°CVinificação Maceração a frio por 72h. Fermentação com temperatura controlada entre 25 e 27ºC por 8 dias.Maturação 4 meses em barricas de carvalhoCorpo MédioPotencial de Guarda 5 anosHarmonizações Churrasco, massas com molho de carne, hamburger Baixar Ficha Técnica Baixar Imagem",
  "caracteristicas": {
    "produtor": "Bodega Cruz de Piedra",
    "pais": "Ver País Argentina Patagonia Chile Portugal Brasil Espanha Ribera del Duero Itália Piemonte Abruzzo Sicilia Provincia de Taranto Toscana França África do Sul",
    "regiao": "Agrelo, Mendoza",
    "tipo": "Tinto",
    "uva": "100% Malbec",
    "volume_ml": 750,
    "safra": "2022",
    "teor_alcoolico_percent": 13.5,
    "temperatura_servico_c": "16°C",
    "vinificacao": "Maceração a frio por 72h. Fermentação com temperatura controlada entre 25 e 27ºC por 8 dias.",
    "maturacao": "4 meses em barricas de carvalho",
    "corpo": "Médio",
    "potencial_guarda_anos": "5 anos",
    "harmonizacoes": [
      "Churrasco",
      "massas com molho de carne",
      "hamburger"
    ]
  },
  "midia": {
    "imagem_principal_url": "https://images.tcdn.com.br/img/img_prod/791130/vin_arg_cruz_de_piedra_deriva_malbec_organico_tto_6x750_ml_377_1_3756b7602afca676c80eae9bfe4b91f2.jpeg",
    "ficha_tecnica_url": "https://drive.usercontent.google.com/u/2/uc?id=14b8pUCl-26OhtSS6dgnGUc4yKjHtjGog&export=download"
  }
}