{
  "codigo_produto": "385",
  "url": "https://www.tdpwines.com.br/vinho-tinto-chileno-go-up-carmenere-reserva-375ml",
  "titulo": "Vinho Tinto GO UP Carménère Reserva 375ml 2021",
  "descricao_geral": "Equilibrado e fácil de beber, este Carménère da GO UP é elaborado no Vale do Curicó, no Chile, uma região do Vale Central reconhecida por seus excelentes rótulos varietais. Com quase 1500 avaliações positivas no Vivino, é frutado, sedoso e macio. Com seis meses de passagem por barricas de carvalho de segundo e terceiro usos, este Carménère apresenta ótima tipicidade, com notas de groselha, amoras, baunilha e pimenta preta. Em boca, é sedoso, com taninos amáveis e acidez gastronômica. Não tem as notas herbáceas e de pirazina que muito incomodam em diversos vinhos da variedade.GO UP Carménère pode ser harmonizado com carnes vermelhas assadas ou grelhadas, como Cordeiro, pizzas, massas com molho à base de carne vermelha e queijos de massa média como o Gouda.A TDP Wines é um projeto em constante busca dos melhores terroirs para a elaboração de vinhos de excelente custo-benefício. Criada pelo enólogo e empreendedor do vinho Tiago Dal Pizzol, a TDP Wines representa o sonho e o compromisso de um apaixonado pela bebida de Baco. CaracteristicasProdutor TDP WinesPais ChileRegião Valle de CuricóTipo TintoUva 100% CarménèreVolume 375mlSafra 2021Teor Alcoólico 13%Temperatura de Serviço 14 a 18°CVinificação Vinificação tradicional em tanques com controle de temperatura (28º a 30ºC).Maturação 6 meses em barricas de carvalho de segundo usoCorpo MédioPotencial de Guarda 3 a 5 anosHarmonizações Carré de cordeiro, carnes vermelhas assadas, queijo parmesão Baixar Ficha Técnica Baixar Imagem",
  "caracteristicas": {
    "produtor": "TDP Wines",
    "pais": "Ver País Argentina Patagonia Chile Portugal Brasil Espanha Ribera del Duero Itália Piemonte Abruzzo Sicilia Provincia de Taranto Toscana França África do Sul",
    "regiao": "Valle de Curicó",
    "tipo": "Tinto",
    "uva": "100% Carménère",
    "volume_ml": 375,
    "safra": "2021",
    "teor_alcoolico_percent": 13.0,
    "temperatura_servico_c": "14 a 18°C",
    "vinificacao": "Vinificação tradicional em tanques com controle de temperatura (28º a 30ºC).",
    "maturacao": "6 meses em barricas de carvalho de segundo uso",
    "corpo": "Médio",
    "potencial_guarda_anos": "3 a 5 anos",
    "harmonizacoes": [
      "Carré de cordeiro",
      "carnes vermelhas assadas",
      "queijo parmesão"
    ]
  },
  "midia": {
    "imagem_principal_url": "https://images.tcdn.com.br/img/img_prod/791130/vinho_tinto_go_up_carmenere_reserva_375ml_2021_385_1_b6dcc113d9e1afec314b088bab3b958e.png",
    "ficha_tecnica_url": "https://drive.usercontent.google.com/uc?id=13WFBZNx7wLb12BWlqPuUIUMf9N491C-s&export=download"
  }
}