{
  "codigo_produto": "243",
  "url": "https://www.tdpwines.com.br/vinho-tinto-espanhol-oh-sister",
  "titulo": "De Andres Sisters Oh! Sister Superiore Rioja Tinto 2022",
  "descricao_geral": "As irmãs Ruth e Ana de Andres têm, com o vinho, uma relação muito bem resolvida. Inquietas, buscam, nos diversos terroirs espanhóis, criar vinhos inspiradores, que surgem após pesquisas, conversas, viagens e muita experimentação.Este tinto de excelente custo-benefício vêm da Rioja, a região que é sinônimo da mais alta qualidade do vinho espanhol. Corte de Tempranillo e Garnacha proveniente de vinhas velhas, com mais de 70 anos, é um vinho muito agradável e bem feito. Com coloração rubi intensa, seu aroma traz muita fruta vermelha fresca, mas madura, junto a notas amadeiradas e especiadas. Em boca, é um vinho muito agradável, de taninos elegantes, corpo médio e longo final.Com seis meses de passagem por barricas de carvalho francês, é perfeito para acompanhar carnes vermelhas grelhadas, massas com molhos vermelhos condimentados, queijos de massa média e embutidos. CaracteristicasProdutor De Andres SistersPais EspanhaRegião RiojaTipo TintoUva Garnacha e Tempranillo de vinhas com mais de 70 anosVolume 750mlSafra 2022Teor Alcoólico 13%Temperatura de Serviço 13°CVinificação Fermentação tradicional com temperatura controladaMaturação 6 meses em carvalho francês de segundo e terceiro usos, mais 5 meses sobre as borras finasCorpo Médio-intensoPotencial de Guarda 5 a 7 anosHarmonizações Carnes vermelhas grelhadas, massas com molhos de carne, queijos de massa dura Baixar Ficha Técnica Baixar Imagem",
  "caracteristicas": {
    "produtor": "De Andres Sisters",
    "pais": "Ver País Argentina Patagonia Chile Portugal Brasil Espanha Ribera del Duero Itália Piemonte Abruzzo Sicilia Provincia de Taranto Toscana França África do Sul",
    "regiao": "Rioja",
    "tipo": "Tinto",
    "uva": "Garnacha e Tempranillo de vinhas com mais de 70 anos",
    "volume_ml": 750,
    "safra": "2022",
    "teor_alcoolico_percent": 13.0,
    "temperatura_servico_c": "13°C",
    "vinificacao": "Fermentação tradicional com temperatura controlada",
    "maturacao": "6 meses em carvalho francês de segundo e terceiro usos, mais 5 meses sobre as borras finas",
    "corpo": "Médio-intenso",
    "potencial_guarda_anos": "5 a 7 anos",
    "harmonizacoes": [
      "Carnes vermelhas grelhadas",
      "massas com molhos de carne",
      "queijos de massa dura"
    ]
  },
  "midia": {
    "imagem_principal_url": "https://images.tcdn.com.br/img/img_prod/791130/de_andres_sisters_oh_sister_superiore_rioja_tinto_243_1_fa98ce7b9955432bae2cb8088ea1c41f_20221003162201.png",
    "ficha_tecnica_url": "https://drive.usercontent.google.com/u/2/uc?id=1HAi0iSoR4AmNN6lmHRzZGYG0JzBNZ0PX&export=download"
  }
}