{
  "codigo_produto": "141",
  "url": "https://www.tdpwines.com.br/vinho-tinto-argentino-gen-del-alma-ji-ji-ji-malbec-pinot-noir",
  "titulo": "Gen del Alma JiJiJi Malbec Pinot Noir 2020",
  "descricao_geral": "92+ pontos Robert ParkerUm clássico que volta ao Brasil, JiJiJi é elaborado na altitude de Gualtallay, no Valle do Uco, pela Gen del Alma, uma inovadora e inquieta vinícola com menos de 10 anos de idade que se destaca pela mescla de ousadia e extrema capacidade de sua equipe enológica.Este vinho não cai longe do pé. JiJiJi Malbec - Pinot Noir é uma co-fermentação das duas variedades que tem como destaque sua complexidade e frescor, características em muito auxiliadas pela maceração carbônica com 100% dos cachos inteiros. Tanto a fermentação quanto a maceração acontecem em grandes ânforas de concreto e o vinho é engarrafado ainda jovem e fresco, o que beneficia seus frescos aromas de frutas vermelhas frescas, como cereja e amora, arrematado por deliciosas notas florais e de especiarias.É perfeito para ser bebido um pouco refrescado, acompanhando pratos que peçam vinhos de maior acidez, como molhos à base de tomate e bacon. CaracteristicasProdutor Gen Del AlmaPais ArgentinaRegião Vale de Tupungato, MendozaTipo TintoUva 50% Malbec, 50% Pinot NoirVolume 750mlSafra 2020Teor Alcoólico 12,5%Temperatura de Serviço 14 a 16°CVinificação 100% maceração carbônica com cachos inteiros. Fermentação em ânforas de concreto a baixa temperatura.Maturação Em ânforas de concretoCorpo MédioPotencial de Guarda 5 anosHarmonizações Massas com molho vermelho, lasanha de beringela, queijos médios. Baixar Ficha Técnica Baixar Imagem",
  "caracteristicas": {
    "produtor": "Gen Del Alma",
    "pais": "Ver País Argentina Patagonia Chile Portugal Brasil Espanha Ribera del Duero Itália Piemonte Abruzzo Sicilia Provincia de Taranto Toscana França África do Sul",
    "regiao": "Vale de Tupungato, Mendoza",
    "tipo": "Tinto",
    "uva": "50% Malbec, 50% Pinot Noir",
    "volume_ml": 750,
    "safra": "2020",
    "teor_alcoolico_percent": 12.5,
    "temperatura_servico_c": "14 a 16°C",
    "vinificacao": "100% maceração carbônica com cachos inteiros. Fermentação em ânforas de concreto a baixa temperatura.",
    "maturacao": "Em ânforas de concreto",
    "corpo": "Médio",
    "potencial_guarda_anos": "5 anos",
    "harmonizacoes": [
      "Massas com molho vermelho",
      "lasanha de beringela",
      "queijos médios"
    ]
  },
  "midia": {
    "imagem_principal_url": "https://images.tcdn.com.br/img/img_prod/791130/gen_del_alma_jijiji_malbec_pinot_noir_2019_141_1_20221003162157.png",
    "ficha_tecnica_url": "https://drive.google.com/u/0/uc?id=1dRDClazwn0cRH5ZVItiVZOTVVDkX0D-5&export=download"
  }
}