{
  "codigo_produto": "vinho-tinto-portugues-bons-anos-douro",
  "url": "https://www.tdpwines.com.br/vinho-tinto-portugues-bons-anos-douro",
  "titulo": "Vinho Tinto Hidrângeas Bons Anos Douro 2017Referência:103112Marca:LusoviniSeja o primeiro a opinar",
  "descricao_geral": "Bons anos, como entrega o nome, é somente elaborado em safras especiais, nas quais as condições são perfeitas para a elaboração de excelentes vinhos. Edição especial de 3000 garrafas, este vinho é um field blend com cerca de 20 castas diferentes, oriundas de vinhas velhas, as quais predominam as Tourigas Franca e Nacional e as Tintas Roriz, Barroca e Amarela, além da Tinto Cão. Para a enóloga Sónia Martins, da Lusovini, o Bons Anos é a materialização do terroir Douro, fruto de muito trabalho nas vinhas e modernização na adega. Da região do Cima Corgo, escolhida pela enóloga por apresentar o melhor equilíbrio, no Douro, entre elegância e fruta madura, Bons Anos começa a ser elaborado da forma mais tradicional possível, com o corte das massas sendo realizado em lagar de granito, por pisa humana. O método, aliado à maceração prolongada, permite uma maior extração de cor e compostos fenólicos. Com seus 18 meses em barricas de carvalho francês novas, Bons Anos tem cor rubi profunda. Seu aroma é bastante expressivo, mostrando de cara as notas terciárias de chocolate preto e charuto, seguidas por fruta vermelha madura como ameixa e framboesa. Em boca é denso, envolvente, com taninos equilibrados no final. É par perfeito para acompanhar pratos regionais do Douro, como o borrego (cordeiro) assado, ou carnes vermelhas assadas. Caracteristicas Produtor Lusovini Pais Portugal Região Douro Tipo Tinto Uva Field Blend de vinhas centenárias, todas de letra A na classificação do IVP Volume 750ml Safra 2017 Teor Alcoólico 13,5% Temperatura de Serviço 16 a 18°C Vinificação Desengace total, diversas remontagens. Corte das massas em lagar típico de granito, com pisa a pé. Leveduras indígenas. Maceração prolongada. Maturação 18 meses em barricas novas de carvalho francês Corpo Intenso Potencial de Guarda Mais de 15 anos Harmonizações Pratos à base de carne; ensopados; queijos curados Baixar Ficha Técnica Baixar Imagem",
  "caracteristicas": {
    "produtor": "Lusovini",
    "pais": "Ver País Argentina Patagonia Chile Portugal Brasil Espanha Ribera del Duero Itália Piemonte Abruzzo Sicilia Provincia de Taranto Toscana França África do Sul",
    "regiao": "Douro",
    "tipo": "Tinto",
    "uva": "Field Blend de vinhas centenárias, todas de letra A na classificação do IVP",
    "volume_ml": 750,
    "safra": "2017",
    "teor_alcoolico_percent": 13.5,
    "temperatura_servico_c": "16 a 18°C",
    "vinificacao": "Desengace total, diversas remontagens. Corte das massas em lagar típico de granito, com pisa a pé. Leveduras indígenas. Maceração prolongada.",
    "maturacao": "18 meses em barricas novas de carvalho francês",
    "corpo": "Intenso",
    "potencial_guarda_anos": "Mais de 15 anos",
    "harmonizacoes": [
      "Pratos à base de carne",
      "ensopados",
      "queijos curados"
    ]
  },
  "midia": {
    "imagem_principal_url": "https://images.tcdn.com.br/img/img_prod/791130/vinho_tinto_hidrangeas_bons_anos_douro_307_1_e9df813d5c80d9d9a56a179e3cf87b44_20221003162148.png",
    "ficha_tecnica_url": "https://drive.usercontent.google.com/u/2/uc?id=1GXNIi0LXB_grYwwekJUBhFXiDGb-Ssbl&export=download"
  }
}