{
  "codigo_produto": "293",
  "url": "https://www.tdpwines.com.br/vinho-tinto-argentino-tapiz-classic-pinot-noir",
  "titulo": "Tapiz Classic Pinot Noir 2022",
  "descricao_geral": "Elaborado pela dupla Fabian Valenzuela, enólogo-chefe com 30 anos de casa, e Jean Claude Berrouet, consultor exclusivo da Tapiz e ex-enólogo do Chateau Pétrus, na França, o Pinot Noir Classic é um vinho de excelente custo-benefício, muito elegante e persistente em boca.Este Pinot Noir é elaborado com uvas de San Pablo, a 1350m de altitude, com um clima mais fresco e noites frias, proporcionando vinhos de salientes notas frutadas e boa acidez. Com passagem de oito meses por barricas de carvalho francês de segundo e terceiro usos, o vinho tem notas sobretudo de frutas vermelhas frescas, junto a especiarias doces e um toque de baunilha. É equilibrado e tem um longo final.Um Pinot Noir clássico, mas de bom corpo, que pode ser harmonizado com uma série de pratos como filé mignon, salmão, comida japonesa e chinesa e risoto de cogumelos. CaracteristicasProdutor TapizPais ArgentinaRegião Vale do Uco, MendozaTipo TintoUva 100% Pinot NoirVolume 750mlSafra 2022Teor Alcoólico 12,4%Temperatura de Serviço 14°CVinificação 5 a 8 dias de maceração préfermentativa a 5-8ºC. 10 a 14 dias de fermentação com temperatura controlada.Maturação 8 meses em barricas de carvalho francês de segundo e terceiro usos.Corpo MédioPotencial de Guarda 6 anosHarmonizações Filé mignon, risoto de funghi, massa alla putanesca. Baixar Ficha Técnica Baixar Imagem",
  "caracteristicas": {
    "produtor": "Tapiz",
    "pais": "Ver País Argentina Patagonia Chile Portugal Brasil Espanha Ribera del Duero Itália Piemonte Abruzzo Sicilia Provincia de Taranto Toscana França África do Sul",
    "regiao": "Vale do Uco, Mendoza",
    "tipo": "Tinto",
    "uva": "100% Pinot Noir",
    "volume_ml": 750,
    "safra": "2022",
    "teor_alcoolico_percent": 12.4,
    "temperatura_servico_c": "14°C",
    "vinificacao": "5 a 8 dias de maceração préfermentativa a 5-8ºC. 10 a 14 dias de fermentação com temperatura controlada.",
    "maturacao": "8 meses em barricas de carvalho francês de segundo e terceiro usos.",
    "corpo": "Médio",
    "potencial_guarda_anos": "6 anos",
    "harmonizacoes": [
      "Filé mignon",
      "risoto de funghi",
      "massa alla putanesca"
    ]
  },
  "midia": {
    "imagem_principal_url": "https://images.tcdn.com.br/img/img_prod/791130/vin_arg_tapiz_classic_pinot_noir_tto_6x750ml_293_1_0a9d565ef89a419cfa47bc52f294e135_20221003162147.jpg",
    "ficha_tecnica_url": "https://drive.usercontent.google.com/u/2/uc?id=1IQN7JQIO42PrzCqikSIj4_n4LSTudGFz&export=download"
  }
}