{
  "codigo_produto": "267",
  "url": "https://www.tdpwines.com.br/vinho-tinto-espanhol-tardencuba-roble-toro",
  "titulo": "Tardencuba DO Toro Roble Tinto 2021",
  "descricao_geral": "90 pontos Robert ParkerTardencuba, localizada em Venialbo, no coração da DO Toro, é um pequeno empreendimento familiar que há três gerações produz vinhos de exceção. A altitude dos apenas três hectares de vinhas pré-filoxericas, junto às noites frias, faz as uvas da família Ramos amadurecem por completo, originando vinhos concentrados, potentes e longevos.Roble, que significa &#39;madeira&#39; em espanhol, já denota a passagem do vinho por barricas de carvalho ? seis meses, em madeira francesa. 100% Tinta de Toro de vinhedos orgânicos com mais de 60 anos, este espanhol é muito representativo da região, com uma linda cor rubi e expressivo aroma, que une notas florais, de frutas negras e vermelhas e especiarias. Em boca, é jugoso, ou suculento, com taninos doces e um frescor que equilibra o potente corpo.É um excelente vinho para acompanhar carne vermelha assada, molhos à base de carne, queijos de massa média e linguiça na churrasqueira. CaracteristicasProdutor TardencubaPais EspanhaRegião ZamoraTipo TintoUva 100% Tinta de Toro, videiras com mais de 60 anos.Volume 750mlSafra 2021Teor Alcoólico 14,5%Temperatura de Serviço 14°CVinificação Fermentação tradicional. Maceração de 20 dias com temperatura controlada em 28ºC.Maturação 06 meses em carvalho mais 12 meses em garrafa.Corpo MédioPotencial de Guarda 5 anosHarmonizações Carnes vermelhas grelhadas, lasanha de beringela. Baixar Ficha Técnica Baixar Imagem",
  "caracteristicas": {
    "produtor": "Tardencuba",
    "pais": "Ver País Argentina Patagonia Chile Portugal Brasil Espanha Ribera del Duero Itália Piemonte Abruzzo Sicilia Provincia de Taranto Toscana França África do Sul",
    "regiao": "Zamora",
    "tipo": "Tinto",
    "uva": "100% Tinta de Toro, videiras com mais de 60 anos.",
    "volume_ml": 750,
    "safra": "2021",
    "teor_alcoolico_percent": 14.5,
    "temperatura_servico_c": "14°C",
    "vinificacao": "Fermentação tradicional. Maceração de 20 dias com temperatura controlada em 28ºC.",
    "maturacao": "06 meses em carvalho mais 12 meses em garrafa.",
    "corpo": "Médio",
    "potencial_guarda_anos": "5 anos",
    "harmonizacoes": [
      "Carnes vermelhas grelhadas",
      "lasanha de beringela"
    ]
  },
  "midia": {
    "imagem_principal_url": "https://images.tcdn.com.br/img/img_prod/791130/tardencuba_do_toro_roble_tinto_2017_267_1_1d9313e4e283790610a8e86f9fc73770_20221003162202.png",
    "ficha_tecnica_url": "https://drive.usercontent.google.com/u/2/uc?id=1Oo306aPYtL_DdUA-Y6udYMBWdrjCCN9k&export=download"
  }
}