{
  "codigo_produto": "261",
  "url": "https://www.tdpwines.com.br/vinho-tinto-espanhol-la-miranda-de-secastilla-garnacha",
  "titulo": "La Miranda de Secastilla Garnacha Tinto 2020",
  "descricao_geral": "91 pontos James Suckling90 pontos IWC88 pontos Guia PeñinMedalha de Ouro Grenaches Du MondeA DO Somontano fica na província de Aragón, aos pés dos Pireneus, cadeia montanhosa que divide a Espanha da França. Os vinhedos de Secastilla ficam em um vale escondido, a cerca de 800 metros acima do nível do mar, onde, tradicionalmente, se cultiva a Garnacha. Não muito conhecida do público, se destaca por apresentar rótulos de excelente custo-benefício, que não raro valem muito mais do que custam.Este tinto é um corte onde predominam Garnachas (85%) de vinhedos velhos junto à Syrah (12%) e à Parraleta (3%). Somontano, para além da Garnacha, também é uma região conhecida pela ótima adaptabilidade das tintas francesas, o que explica a presença da variedade típica do Rhône no blend. Com 8 meses de passagem por barricas de carvalho francês, é um vinho muito vivo em boca, complexo e com final de frutas vermelhas. No nariz, frutas vermelhas, framboesa, ameixa, baunilha e toffee.É companhia perfeita para carnes grelhadas, como bisteca suína e fraldinha, e massas com molhos vermelhos. CaracteristicasProdutor Viñas del VeroPais EspanhaRegião SomontanoTipo TintoUva 85% Garnacha, 12% Syrah e 3% Parraleta.Volume 750mlSafra 2020Teor Alcoólico 13,5%Temperatura de Serviço 14°CVinificação Colheita manual. Maceração pré-fermentativa por 2 dias. Fermentação com leveduras indígenas por 10 dias a 25ºC.Maturação 8 meses em barricas de carvalho francês.Corpo MédioPotencial de Guarda 7 a 10 anosHarmonizações Cordeiro, bisteca suína, massas com molhos vermelhos. Baixar Ficha Técnica Baixar Imagem",
  "caracteristicas": {
    "produtor": "Viñas del Vero",
    "pais": "Ver País Argentina Patagonia Chile Portugal Brasil Espanha Ribera del Duero Itália Piemonte Abruzzo Sicilia Provincia de Taranto Toscana França África do Sul",
    "regiao": "Somontano",
    "tipo": "Tinto",
    "uva": "85% Garnacha, 12% Syrah e 3% Parraleta.",
    "volume_ml": 750,
    "safra": "2020",
    "teor_alcoolico_percent": 13.5,
    "temperatura_servico_c": "14°C",
    "vinificacao": "Colheita manual. Maceração pré-fermentativa por 2 dias. Fermentação com leveduras indígenas por 10 dias a 25ºC.",
    "maturacao": "8 meses em barricas de carvalho francês.",
    "corpo": "Médio",
    "potencial_guarda_anos": "7 a 10 anos",
    "harmonizacoes": [
      "Cordeiro",
      "bisteca suína",
      "massas com molhos vermelhos"
    ]
  },
  "midia": {
    "imagem_principal_url": "https://images.tcdn.com.br/img/img_prod/791130/la_miranda_de_secastilla_garnacha_tinto_2018_261_1_64f483f67988fc92ac476d790cccc07d_20221003162201.png",
    "ficha_tecnica_url": "https://drive.usercontent.google.com/u/2/uc?id=1FxOhP6AuNmD6HDzqQeyqQFkUY5Sy-hsl&export=download"
  }
}