{
  "codigo_produto": "vinho-tinto-portugues-pedra-cancela-touriga-nacional",
  "url": "https://www.tdpwines.com.br/vinho-tinto-portugues-pedra-cancela-touriga-nacional",
  "titulo": "Pedra Cancela Touriga Nacional Tinto 2014Referência:103213Marca:LusoviniSeja o primeiro a opinar",
  "descricao_geral": "Para o crítico e produtor de vinhos português Pedro Garcias, este vinho resume 'o que é o Dão' e sua casta mais emblemática, a Touriga Nacional. Pedra Cancela, no coração de Nelas, é um projeto que se propõe resgatar o que há de mais tradicional no Dão, unindo-o à modernidade que os tempos exigem. Tinto vermelho, profundo, com notas de lavanda e violeta, juntamente com fruta bem madura, é aveludado e cheio, com potencial para muitos anos de guarda. Passa 12 meses em contato com barricas francesas novas e de segundo uso. Bastante complexo, harmoniza muito bem com pratos típicos da culinária do Dão, como a Posta à Mirandesa, bife alto, de gado endêmico, preparado na brasa. Caracteristicas Produtor Lusovini Pais Portugal Região Dão Tipo Tinto Uva 100% Touriga Nacional Volume 750ml Safra 2014 Teor Alcoólico 13,5% Temperatura de Serviço 14 a 16°C Vinificação Fermentação em lagar típico de granito com alguma maceração e temperatura controlada a 24ºC. Maturação 12 meses em barricas de carvalho francês. Corpo Intenso Potencial de Guarda 6 a 8 anos Harmonizações Contra filé grelhado e arroz de pato. Baixar Ficha Técnica Baixar Imagem",
  "caracteristicas": {
    "produtor": "Lusovini",
    "pais": "Ver País Argentina Patagonia Chile Portugal Brasil Espanha Ribera del Duero Itália Piemonte Abruzzo Sicilia Provincia de Taranto Toscana França África do Sul",
    "regiao": "Dão",
    "tipo": "Tinto",
    "uva": "100% Touriga Nacional",
    "volume_ml": 750,
    "safra": "2014",
    "teor_alcoolico_percent": 13.5,
    "temperatura_servico_c": "14 a 16°C",
    "vinificacao": "Fermentação em lagar típico de granito com alguma maceração e temperatura controlada a 24ºC.",
    "maturacao": "12 meses em barricas de carvalho francês.",
    "corpo": "Intenso",
    "potencial_guarda_anos": "6 a 8 anos",
    "harmonizacoes": [
      "Contra filé grelhado",
      "arroz de pato"
    ]
  },
  "midia": {
    "imagem_principal_url": "https://images.tcdn.com.br/img/img_prod/791130/pedra_cancela_touriga_nacional_tinto_2014_189_1_56bd9dbf9747e1eeffb5d1894ef94840_20221003162143.png",
    "ficha_tecnica_url": "https://drive.usercontent.google.com/u/2/uc?id=1LddB-10a3Jj2GR7iU8fL8jpV8d4_WbGO&export=download"
  }
}