{
  "codigo_produto": "257",
  "url": "https://www.tdpwines.com.br/vinho-rose-italiano-mediterranico-mascalese-syrah-terre-siciliane",
  "titulo": "Vinho Rosé Mediterranico IGT Terre Siciliane 2022",
  "descricao_geral": "Jovens e modernos, os vinhos de vinhedos orgânicos e veganos da Mediterranico são elaborados com as castas de melhor qualidade da Sicília, como a Pinot Grigio, Nero DAvola e Nerello Mascalese. São vinhos frescos, com grande influência marítima e de ótimo custo-benefício.Este rosé da Sicília, na costa mediterrânea, proveniente de vinhas orgânicas certificadas, tem na fruta fresca e equilíbrio entre corpo e acidez suas grandes características.O rótulo é um corte de Syrah, muito bem adaptada ao terroir da Sicília, e da local Nerello Mascalese, uma variedade de grande importância na região do vulcão Etna e que origina vinhos alcoólicos, com boa acidez e taninos delicados. Este rosé, portanto, une estas características às notas especiadas da Syrah para fazer um rosé de bom corpo, perfeito para o verão e também para acompanhar aperitivos, entradas, tábua de frios e sushi. CaracteristicasProdutor SettesoliPais ItáliaRegião SicíliaTipo RoséUva Syrah e Nerello MascaleseVolume 750mlSafra 2022Teor Alcoólico 12,5%Temperatura de Serviço 8°CVinificação Fermentação tradicional com controle de temperatura.Maturação Tanques de aço inoxCorpo MédioPotencial de Guarda 3 anosHarmonizações Frios e embutidos, caldos e sopas de peixes, massas e risotos de frutos do mar. Baixar Ficha Técnica Baixar Imagem",
  "caracteristicas": {
    "produtor": "Settesoli",
    "pais": "Ver País Argentina Patagonia Chile Portugal Brasil Espanha Ribera del Duero Itália Piemonte Abruzzo Sicilia Provincia de Taranto Toscana França África do Sul",
    "regiao": "Sicília",
    "tipo": "Rosé",
    "uva": "Syrah e Nerello Mascalese",
    "volume_ml": 750,
    "safra": "2022",
    "teor_alcoolico_percent": 12.5,
    "temperatura_servico_c": "8°C",
    "vinificacao": "Fermentação tradicional com controle de temperatura.",
    "maturacao": "Tanques de aço inox",
    "corpo": "Médio",
    "potencial_guarda_anos": "3 anos",
    "harmonizacoes": [
      "Frios",
      "embutidos",
      "caldos",
      "sopas de peixes",
      "massas",
      "risotos de frutos do mar"
    ]
  },
  "midia": {
    "imagem_principal_url": "https://images.tcdn.com.br/img/img_prod/791130/vin_ita_mediterranico_ner_mascalese_syrah_terre_siciliane_rose_6_x_750_ml_257_1_92ca449b23e7ed137a5c0c9b48af6b2e_20221003162156.png",
    "ficha_tecnica_url": "https://drive.usercontent.google.com/u/2/uc?id=1j9xks9jIsjpFecaKdvzzuvc7DJaizKNm&export=download"
  }
}