{
  "codigo_produto": "247",
  "url": "https://www.tdpwines.com.br/vinho-tinto-italiano-menhir-salice-salentino-doc",
  "titulo": "Menhir Salento Salice Salentino DOC 2021",
  "descricao_geral": "A cantina Menhir Salento une o conhecimento de ontem com as possibilidades do amanhã. Respeitando a tradição, traz, com uma vinícola moderna e produção agrícola integrada, alguns dos vinhos mais interessantes da região de Lecce, no ?salto da bota? italiana.Os vinhos da DOC Salice Salentino são os mais tradicionais e bem conceituados da região de Salento. Sempre um corte das clássicas uvas da região, Negroamaro e Malvasia Nera, este tinto, com 80% da primeira e 20% da segunda, é elaborado a partir de uvas de vinhedos com idades entre 50 e 60 anos.Com 18 meses de passagem por barricas de carvalho francês e americano, é muito encorpado e quente, típico dos vinhos desta denominação. O aroma é bastante potente, com notas de frutas vermelhas e negras maduras, como mirtilo e amora, junto a especiarias como cravo, canela e uma not balsâmica.Em boca, é quente e potente, apoiado por um tanino harmônico e maduro, de final muito rico e longo. É um excelente vinho para acompanhar carnes assadas, pratos com cogumelo porcini e trufas e queijos de massas média ou dura. CaracteristicasProdutor Menhir SalentoPais ItáliaRegião SalentoTipo TintoUva 80% Negroamaro, 20% Malvasia NeraVolume 750mlSafra 2021Teor Alcoólico 13%Temperatura de Serviço 16°CVinificação Colheita Manual. Fermentação tradicional com temperatura a 22-24ºC por 10 dias.Maturação 6 meses em barricas de carvalho francês e americano de segundo uso.Corpo EncorpadoPotencial de Guarda 7 anosHarmonizações Carne vermelha grelhada, carne de caça, queijos maturados. Baixar Ficha Técnica Baixar Imagem",
  "caracteristicas": {
    "produtor": "Menhir Salento",
    "pais": "Ver País Argentina Patagonia Chile Portugal Brasil Espanha Ribera del Duero Itália Piemonte Abruzzo Sicilia Provincia de Taranto Toscana França África do Sul",
    "regiao": "Salento",
    "tipo": "Tinto",
    "uva": "80% Negroamaro, 20% Malvasia Nera",
    "volume_ml": 750,
    "safra": "2021",
    "teor_alcoolico_percent": 13.0,
    "temperatura_servico_c": "16°C",
    "vinificacao": "Colheita Manual. Fermentação tradicional com temperatura a 22-24ºC por 10 dias.",
    "maturacao": "6 meses em barricas de carvalho francês e americano de segundo uso.",
    "corpo": "Encorpado",
    "potencial_guarda_anos": "7 anos",
    "harmonizacoes": [
      "Carne vermelha grelhada",
      "carne de caça",
      "queijos maturados"
    ]
  },
  "midia": {
    "imagem_principal_url": "https://images.tcdn.com.br/img/img_prod/791130/menhir_salento_quota_29_primitivo_di_salento_igt_2020_247_1_3d5407b4df77fb92dad4814dde8b5ddc_20221003162202.png",
    "ficha_tecnica_url": "https://drive.usercontent.google.com/u/2/uc?id=1jIIC0GA-KNFcVvsqiHPLib-xr9I2oQ07&export=download"
  }
}