{
  "codigo_produto": "139",
  "url": "https://www.tdpwines.com.br/vinho-branco-argentino-gen-del-alma-ji-ji-ji-chenin-blanc",
  "titulo": "Gen del Alma JiJiJi Chenin Blanc 2020",
  "descricao_geral": "93 pontos Descorchados92 pontos Robert ParkerUm clássico que volta ao Brasil, este JiJiJi branco é elaborado na altitude de Tunuyán, no Valle do Uco, pela Gen del Alma, uma inovadora e inquieta vinícola com menos de 10 anos de idade que se destaca pela mescla de ousadia e extrema capacidade de sua equipe enológica.Um raro argentino de Chenin Blanc, este vinho é para os amantes dos brancos frescos e vibrantes. A vinificação tem caráter minimalista, com o uso de leveduras indígenas e maturação sobre as borras por seis meses, com o vinho armazenado em grandes ânforas de concreto. É engarrafado sem filtração e tem uma linda complexidade de aromas, com destaque para as frutas cítricas, principalmente limão sicilianol; de polpa branca, como melão, e notas florais e minerais.Em boca é super fresco, energético, com um final que alia salinidade e mineralidade. É perfeito para acompanhar pratos com frutos do mar, peixes e carnes brancas. CaracteristicasProdutor Gen Del AlmaPais ArgentinaRegião Vale de Tupungato, MendozaTipo BrancoUva 100% Chenin BlancVolume 750mlSafra 2020Teor Alcoólico 11%Temperatura de Serviço 8 a 10°CVinificação Pré-maceração em frio, com as peles. Fermentação em ânforas de concreto a baixa temperatura.Maturação Em ânforas de concretoCorpo MédioPotencial de Guarda 5 anosHarmonizações Saladas, peixes grelhados ou com molho branco, carnes brancas. Baixar Ficha Técnica Baixar Imagem",
  "caracteristicas": {
    "produtor": "Gen Del Alma",
    "pais": "Ver País Argentina Patagonia Chile Portugal Brasil Espanha Ribera del Duero Itália Piemonte Abruzzo Sicilia Provincia de Taranto Toscana França África do Sul",
    "regiao": "Vale de Tupungato, Mendoza",
    "tipo": "Branco",
    "uva": "100% Chenin Blanc",
    "volume_ml": 750,
    "safra": "2020",
    "teor_alcoolico_percent": 11.0,
    "temperatura_servico_c": "8 a 10°C",
    "vinificacao": "Pré-maceração em frio, com as peles. Fermentação em ânforas de concreto a baixa temperatura.",
    "maturacao": "Em ânforas de concreto",
    "corpo": "Médio",
    "potencial_guarda_anos": "5 anos",
    "harmonizacoes": [
      "Saladas",
      "peixes grelhados ou com molho branco",
      "carnes brancas"
    ]
  },
  "midia": {
    "imagem_principal_url": "https://images.tcdn.com.br/img/img_prod/791130/gen_del_alma_jijiji_chenin_blanc_2019_139_1_20221003162151.png",
    "ficha_tecnica_url": "https://drive.google.com/u/0/uc?id=1DBRBsMIlO80nPexzJAMjAViQKg_yJcO0&export=download"
  }
}