{
  "codigo_produto": "259",
  "url": "https://www.tdpwines.com.br/vinho-tinto-espanhol-secastilla-garnacha",
  "titulo": "Secastilla Viñedos Viejos Garnacha 2017",
  "descricao_geral": "93 pontos Guia Peñin92 pontos DecanterA DO Somontano fica na província de Aragón, aos pés dos Pireneus, cadeia montanhosa que divide a Espanha da França. Os vinhedos de Secastilla ficam em um vale escondido, a cerca de 800 metros acima do nível do mar, onde, tradicionalmente, se cultiva a Garnacha. Não muito conhecida do público, se destaca por apresentar rótulos de excelente custo-benefício, que não raro valem muito mais do que custam.Este Garnacha vem de vinhas muito antigas, com mais de oitenta anos, fruto de um trabalho de resgate e conservação iniciado pela Viñas del Vero no final da década de 1990. Cultivadas no sistema de vasos, originam um vinho que une elegância e profundidade, com aroma de frutas vermelhas ácidas, como cerejas e amoras, notas medicinais, de madeira e de folhas molhadas.Em boca, abre-se com muita complexidade, com taninos muito elegantes e maduros, corpo sedoso, e final muito longo.É perfeito para acompanhar carnes de caça, carnes vermelhas grelhadas e queijos curados. CaracteristicasProdutor Viñas del VeroPais EspanhaRegião SomontanoTipo TintoUva 100% Garnacha de Vinhas VelhasVolume 750mlSafra 2017Teor Alcoólico 14%Temperatura de Serviço 14°CVinificação Colheita manual. Maceração pré-fermentativa por 3 dias. Fermentação com leveduras indígenas com temperatura controlada.Maturação 10 meses em barricas de carvalho francêsCorpo MuitoPotencial de Guarda 15 anosHarmonizações Cordeiro, bisteca suína, massas com molhos vermelhos. Baixar Ficha Técnica Baixar Imagem",
  "caracteristicas": {
    "produtor": "Viñas del Vero",
    "pais": "Ver País Argentina Patagonia Chile Portugal Brasil Espanha Ribera del Duero Itália Piemonte Abruzzo Sicilia Provincia de Taranto Toscana França África do Sul",
    "regiao": "Somontano",
    "tipo": "Tinto",
    "uva": "100% Garnacha de Vinhas Velhas",
    "volume_ml": 750,
    "safra": "2017",
    "teor_alcoolico_percent": 14.0,
    "temperatura_servico_c": "14°C",
    "vinificacao": "Colheita manual. Maceração pré-fermentativa por 3 dias. Fermentação com leveduras indígenas com temperatura controlada.",
    "maturacao": "10 meses em barricas de carvalho francês",
    "corpo": "Muito",
    "potencial_guarda_anos": "15 anos",
    "harmonizacoes": [
      "Cordeiro",
      "bisteca suína",
      "massas com molhos vermelhos"
    ]
  },
  "midia": {
    "imagem_principal_url": "https://images.tcdn.com.br/img/img_prod/791130/secastilla_vinedos_viejos_garnacha_2016_259_1_f94394db945ead519b12c77c52f401bf_20221003162202.png",
    "ficha_tecnica_url": "https://drive.usercontent.google.com/u/2/uc?id=1FtIj7BagYkjmnqZhlrxW_U-Fd3vQdMUJ&export=download"
  }
}