{
  "codigo_produto": "291",
  "url": "https://www.tdpwines.com.br/vinho-branco-argentino-tapiz-classic-torrontes",
  "titulo": "Tapiz Classic Torrontés 2023",
  "descricao_geral": "Elaborado pela dupla Fabian Valenzuela, enólogo-chefe com 30 anos de casa, e Jean Claude Berrouet, consultor exclusivo da Tapiz e ex-enólogo do Chateau Pétrus, na França, este delicioso Torrontés de Alto Agrelo é muito fresco e perfumado.Este Torrontés é elaborado com uvas da Finca El Jarillal, em Alto Agrelo, no coração de Mendoza, uma região com vinhedos muito inclinados e equilíbrio entre noites frescas e muito boa insolação durante o dia. Sem passagem por carvalho e com apenas 10% do vinho fazendo fermentação malolática, este branco se destaca pelas notas perfumadas de flores, como jasmim e rosas, além da presença de frutas cítricas, como lima da pérsia. É muito fresco, elegante e com longo final.Um jovem e delicado vinho branco que vai muito bem com saladas de folhas verdes, peixes grelhados e carnes brancas grelhadas. CaracteristicasProdutor TapizPais ArgentinaRegião Agrelo, Luján de CuyoTipo BrancoUva 100% TorrontésVolume 750mlSafra 2023Teor Alcoólico 13,9%Temperatura de Serviço 8 a 10°CVinificação Fermentação alcoólica a baixas temperaturas. Apenas 10% do vinho faz fermentação malolática.Maturação Tanques de aço inoxCorpo LevePotencial de Guarda 4 anosHarmonizações Saladas verdes, peixes grelhados. Baixar Ficha Técnica Baixar Imagem",
  "caracteristicas": {
    "produtor": "Tapiz",
    "pais": "Ver País Argentina Patagonia Chile Portugal Brasil Espanha Ribera del Duero Itália Piemonte Abruzzo Sicilia Provincia de Taranto Toscana França África do Sul",
    "regiao": "Agrelo, Luján de Cuyo",
    "tipo": "Branco",
    "uva": "100% Torrontés",
    "volume_ml": 750,
    "safra": "2023",
    "teor_alcoolico_percent": 13.9,
    "temperatura_servico_c": "8 a 10°C",
    "vinificacao": "Fermentação alcoólica a baixas temperaturas. Apenas 10% do vinho faz fermentação malolática.",
    "maturacao": "Tanques de aço inox",
    "corpo": "Leve",
    "potencial_guarda_anos": "4 anos",
    "harmonizacoes": [
      "Saladas verdes",
      "peixes grelhados"
    ]
  },
  "midia": {
    "imagem_principal_url": "https://images.tcdn.com.br/img/img_prod/791130/vin_arg_tapiz_classic_torrontes_bco_6x750ml_291_1_11462eb014a511cc45f5874dbea2d0aa_20221003162154.jpg",
    "ficha_tecnica_url": "https://drive.usercontent.google.com/u/2/uc?id=1HwpOVP_KboFNndDmvb6ZhSDsJFuPOqL9&export=download"
  }
}