{
  "codigo_produto": "197",
  "url": "https://www.tdpwines.com.br/vinho-tinto-chileno-primus-winemaker-selection",
  "titulo": "Primus Winemaker Selection 2018",
  "descricao_geral": "Primus, que em latim significa &#39;primeiro entre seus pares&#39;. Seus vinhos nascem na época em que a visão do vinho chileno era muito conservadora, voltada principalmente para vinhos monovarietais. O fundador, um visionário, resolve mesclar parcelas de seus melhores vinhos, surgindo assim um grande nome do vinho chileno.Primus Winemaker Selection é elaborado pela chilena Veramonte, mesma proprietária das marcas Ritual e Neyen, reconhecida pela seriedade no trabalho e comprometimento com a qualidade de seus vinhos. É um corte de Carménère (70%), Syrah (25%) e Cabernet Franc (5%) elaborado com uvas de diferentes parcelas da propriedade de Apalta, no vale de Colchagua. Enquanto a Syrah e a Cabernet Franc vêm das ladeiras mais altas, a Carménère vem das antigas terraças do rio Tinguiririca, de vinhas velhas com mais de oitenta anos de idade. Todos os vinhedos são orgânicos.O vinho é espetacular, um clássico tinto de Apalta, com excelente drinkability e longa persistência, sendo perfeito para qualquer prato à base de caça ou carne vermelha. Com passagem de 14 meses por barricas de carvalho francês novas, no nariz tem muita fruta negra madura, como mirtilo, ameixa e amora, junto a notas de café, chocolate e cogumelos. Em boca, acidez moderada, taninos sedodos, boa concentração e longo final. CaracteristicasProdutor VeramontePais ChileRegião ApaltaTipo TintoUva 70% Carménère, 25% Syrah, 5% Cabernet Franc.Volume 750mlSafra 2018Teor Alcoólico 14%Temperatura de Serviço 14 a 16°CVinificação Vinificação tradicional, fermentação com leveduras indígenas.Maturação 14 meses em barricas de carvalho francês.Corpo IntensoPotencial de Guarda 10 a 15 anosHarmonizações Cozidos à base de carne vermelha, como boeuf bourguignon, carnes de caça. Baixar Ficha Técnica Baixar Imagem",
  "caracteristicas": {
    "produtor": "Veramonte",
    "pais": "Ver País Argentina Patagonia Chile Portugal Brasil Espanha Ribera del Duero Itália Piemonte Abruzzo Sicilia Provincia de Taranto Toscana França África do Sul",
    "regiao": "Apalta",
    "tipo": "Tinto",
    "uva": "70% Carménère, 25% Syrah, 5% Cabernet Franc.",
    "volume_ml": 750,
    "safra": "2018",
    "teor_alcoolico_percent": 14.0,
    "temperatura_servico_c": "14 a 16°C",
    "vinificacao": "Vinificação tradicional, fermentação com leveduras indígenas.",
    "maturacao": "14 meses em barricas de carvalho francês.",
    "corpo": "Intenso",
    "potencial_guarda_anos": "10 a 15 anos",
    "harmonizacoes": [
      "Cozidos à base de carne vermelha",
      "como boeuf bourguignon",
      "carnes de caça"
    ]
  },
  "midia": {
    "imagem_principal_url": "https://images.tcdn.com.br/img/img_prod/791130/primus_winemaker_selection_2016_197_1_10c1b4557e37d086958a2101f22e39ac_20221003162142.png",
    "ficha_tecnica_url": "https://drive.usercontent.google.com/u/2/uc?id=1OHmoZ7IoS11O_FiD57fU6QBx7RpbvqdI&export=download"
  }
}