{
  "codigo_produto": "397",
  "url": "https://www.tdpwines.com.br/vinho-branco-chileno-veramonte-gran-reserva-chardonnay",
  "titulo": "Veramonte Gran Reserva Chardonnay 2023",
  "descricao_geral": "Típico Chardonnay do Vale de Casablanca, fresco, de corpo médio, com notas de frutas de caroço maduras, limão siciliano e baunilha. Certificadamente orgânico. CaracteristicasProdutor VeramontePais ChileRegião CasablancaTipo BrancoUva 100% ChardonnayVolume 750mlSafra 2023Teor Alcoólico 13,8%Temperatura de Serviço 8 a 12°CVinificação Prensagem dos cachos inteiros. Fermentação parte em barricas de carvalho neutras e parte em tanques de aço inox, com battonage.Maturação 6 meses em barricas de carvalho francês.Corpo MédioPotencial de Guarda 5 anosHarmonizações Salmão, atum e carnes brancas grelhadas. Massas com molhos brancos. Baixar Ficha Técnica Baixar Imagem",
  "caracteristicas": {
    "produtor": "Veramonte",
    "pais": "Ver País Argentina Patagonia Chile Portugal Brasil Espanha Ribera del Duero Itália Piemonte Abruzzo Sicilia Provincia de Taranto Toscana França África do Sul",
    "regiao": "Casablanca",
    "tipo": "Branco",
    "uva": "100% Chardonnay",
    "volume_ml": 750,
    "safra": "2023",
    "teor_alcoolico_percent": 13.8,
    "temperatura_servico_c": "8 a 12°C",
    "vinificacao": "Prensagem dos cachos inteiros. Fermentação parte em barricas de carvalho neutras e parte em tanques de aço inox, com battonage.",
    "maturacao": "6 meses em barricas de carvalho francês.",
    "corpo": "Médio",
    "potencial_guarda_anos": "5 anos",
    "harmonizacoes": [
      "Salmão",
      "atum",
      "carnes brancas grelhadas. Massas com molhos brancos"
    ]
  },
  "midia": {
    "imagem_principal_url": "https://images.tcdn.com.br/img/img_prod/791130/veramonte_gran_reserva_chardonnay_2023_397_1_e80d19ca133e9b8fda89fee71571551c.png",
    "ficha_tecnica_url": "https://drive.usercontent.google.com/uc?id=1KLrGhwRkFfd6DEWje5oXe2PrcIpmA4Kn&export=download"
  }
}