{
  "codigo_produto": "379",
  "url": "https://www.tdpwines.com.br/vinho-tinto-oganico-argentino-garbo-cabernet-franc-cruz-de-piedra",
  "titulo": "Vinho Orgânico Tinto Garbo Cruz de Piedra Cabernet Franc 2022",
  "descricao_geral": "Cabernet Franc é cada vez mais plantada na Argentina, e com grande sucesso. Este tinto certificadamente orgânico traz notas de cerejas e framboesas, complementadas pelo toque de especiarias, tabaco e sândalo dado pela passagem por madeira. Tem grande corpo, boa complexidade e uma ótima sensação em boca, com taninos presentes mas muito bem trabalhados.Acompanha carnes vermelhas assadas, como cordeiro e vitela, bem como molhos condimentados que levem vinho em seu preparo.Seu produtor, a bodega Cruz de Piedra, tem mais de cinquenta anos de história na mais tradicional zona produtora argentina, Mendoza. Localizada em na zona de mesmo nome, Cruz de Piedra, dentro da chamada Primeira Zona, aos pés da Cordilheira dos Andes, na área de Maipú, a vinícola inspirou-se, em seu início, nos vinhos americanos da Califórnia, especialmente nos varietais elaborados 100% com uma única variedade. CaracteristicasProdutor Bodega Cruz de PiedraPais ArgentinaRegião Agrelo, MendozaTipo TintoUva 100% Cabernet FrancVolume 750mlSafra 2022Teor Alcoólico 14%Temperatura de Serviço 16°CVinificação Maceração a frio por 2 dias. Fermentação por 7 dias entre 24 e 26ºC.Maturação 30% em barricas de carvalho de 500l e o restante em foudres de carvalho de 3500l.Corpo MuitoPotencial de Guarda 10 anosHarmonizações Carne assada, cordeiro Baixar Ficha Técnica Baixar Imagem",
  "caracteristicas": {
    "produtor": "Bodega Cruz de Piedra",
    "pais": "Ver País Argentina Patagonia Chile Portugal Brasil Espanha Ribera del Duero Itália Piemonte Abruzzo Sicilia Provincia de Taranto Toscana França África do Sul",
    "regiao": "Agrelo, Mendoza",
    "tipo": "Tinto",
    "uva": "100% Cabernet Franc",
    "volume_ml": 750,
    "safra": "2022",
    "teor_alcoolico_percent": 14.0,
    "temperatura_servico_c": "16°C",
    "vinificacao": "Maceração a frio por 2 dias. Fermentação por 7 dias entre 24 e 26ºC.",
    "maturacao": "30% em barricas de carvalho de 500l e o restante em foudres de carvalho de 3500l.",
    "corpo": "Muito",
    "potencial_guarda_anos": "10 anos",
    "harmonizacoes": [
      "Carne assada",
      "cordeiro"
    ]
  },
  "midia": {
    "imagem_principal_url": "https://images.tcdn.com.br/img/img_prod/791130/vin_arg_cruz_de_piedra_garbo_cabernet_franc_organico_tto_6x750_ml_379_1_7bbd0ea3ee77708648c10b225cce6fae.jpeg",
    "ficha_tecnica_url": "https://drive.usercontent.google.com/u/2/uc?id=14dpc_4OY2_EPGFrFZZH4wSTtpkw0tFqm&export=download"
  }
}