{
  "codigo_produto": "381",
  "url": "https://www.tdpwines.com.br/vinho-branco-organico-argentino-deriva-pinot-grigio-cruz-de-piedra",
  "titulo": "Vinho Orgânico Branco Argentino Deriva Pinot Grigio Cruz de Piedra 2023",
  "descricao_geral": "Certificadamente orgânico, este branco traz uma variedade não tão comum na Argentina, a Pinot Grigio. No nariz, destacam-se as notas florais e de frutas tropicais como pêssego e damasco. Em boca, é leve e fresco, com uma muito boa acidez e persistência em boca.Vai muito bem com pratos leves à base de carnes brancas grelhadas e também saladas.Seu produtor, a bodega Cruz de Piedra, tem mais de cinquenta anos de história na mais tradicional zona produtora argentina, Mendoza. Localizada em na zona de mesmo nome, Cruz de Piedra, dentro da chamada Primeira Zona, aos pés da Cordilheira dos Andes, na área de Maipú, a vinícola inspirou-se, em seu início, nos vinhos americanos da Califórnia, especialmente nos varietais elaborados 100% com uma única variedade. CaracteristicasProdutor Bodega Cruz de PiedraPais ArgentinaRegião Agrelo, MendozaTipo BrancoUva 100% Pinot GrigioVolume 750mlSafra 2023Teor Alcoólico 12,5%Temperatura de Serviço 8 a 10°CVinificação Fermentação com temperatura controlada entre 14 e 16ºC por 28 dias.Maturação Tanques de aço inoxCorpo LevePotencial de Guarda 5 anosHarmonizações Frutos do mar, salada, peixes. Baixar Ficha Técnica Baixar Imagem",
  "caracteristicas": {
    "produtor": "Bodega Cruz de Piedra",
    "pais": "Ver País Argentina Patagonia Chile Portugal Brasil Espanha Ribera del Duero Itália Piemonte Abruzzo Sicilia Provincia de Taranto Toscana França África do Sul",
    "regiao": "Agrelo, Mendoza",
    "tipo": "Branco",
    "uva": "100% Pinot Grigio",
    "volume_ml": 750,
    "safra": "2023",
    "teor_alcoolico_percent": 12.5,
    "temperatura_servico_c": "8 a 10°C",
    "vinificacao": "Fermentação com temperatura controlada entre 14 e 16ºC por 28 dias.",
    "maturacao": "Tanques de aço inox",
    "corpo": "Leve",
    "potencial_guarda_anos": "5 anos",
    "harmonizacoes": [
      "Frutos do mar",
      "salada",
      "peixes"
    ]
  },
  "midia": {
    "imagem_principal_url": "https://images.tcdn.com.br/img/img_prod/791130/vinho_branco_argentino_deriva_pinot_grigio_cruz_de_piedra_2021_381_1_778e6f50ef4fc1022d5d4cafac12e19c.jpeg",
    "ficha_tecnica_url": "https://drive.usercontent.google.com/u/2/uc?id=14ddHw9AURkwvYKWH3cIWOLnV7qwhnUm1&export=download"
  }
}