{
  "codigo_produto": "253",
  "url": "https://www.tdpwines.com.br/vinho-branco-italiano-mediterranico-pinot-grigio-sicilia",
  "titulo": "Mediterranico Pinot Grigio IGT Terre Siciliane 2022",
  "descricao_geral": "Jovens e modernos, os vinhos orgânicos e veganos da Mediterranico são elaborados com as castas de melhor qualidade da Sicília, como a Pinot Grigio, Nero DAvola e Nerello Mascalese. São vinhos frescos, com grande influência marítima e de ótimo custo-benefício.A Pinot Grigio, uma das brancas de maior sucesso na Itália, tem diferentes expressões dependendo do local onde é cultivada. Este branco elaborado às margens do Mediterrâneo é delicado e refrescante, porém com um corpo maior e acidez mais moderada em relação aos elaborados no norte da Itália. Tem agradáveis notas cítricas, florais e de frutas de caroço.É excelente companhia para as jornadas mais quentes e para pratos leves como peixes grelhados e saladas. CaracteristicasProdutor SettesoliPais ItáliaRegião SicíliaTipo BrancoUva Pinot GrigioVolume 750mlSafra 2022Teor Alcoólico 12%Temperatura de Serviço 6 a 8°CVinificação Fermentação tradicional com controle de temperatura.Maturação Tanques de aço inoxCorpo MédioPotencial de Guarda 3 anosHarmonizações Mariscos, peixes brancos grelhados, saladas Baixar Ficha Técnica Baixar Imagem",
  "caracteristicas": {
    "produtor": "Settesoli",
    "pais": "Ver País Argentina Patagonia Chile Portugal Brasil Espanha Ribera del Duero Itália Piemonte Abruzzo Sicilia Provincia de Taranto Toscana França África do Sul",
    "regiao": "Sicília",
    "tipo": "Branco",
    "uva": "Pinot Grigio",
    "volume_ml": 750,
    "safra": "2022",
    "teor_alcoolico_percent": 12.0,
    "temperatura_servico_c": "6 a 8°C",
    "vinificacao": "Fermentação tradicional com controle de temperatura.",
    "maturacao": "Tanques de aço inox",
    "corpo": "Médio",
    "potencial_guarda_anos": "3 anos",
    "harmonizacoes": [
      "Mariscos",
      "peixes brancos grelhados",
      "saladas"
    ]
  },
  "midia": {
    "imagem_principal_url": "https://images.tcdn.com.br/img/img_prod/791130/vin_ita_mediterranico_pinot_grigio_sicilia_branco_6_x_750_ml_253_1_4419950785cc4fa514996a73725b56f3_20221003162153.png",
    "ficha_tecnica_url": "https://drive.usercontent.google.com/u/2/uc?id=1j7dQjpnd2VL6tbT_FzMy8JT_Gakn4yzr&export=download"
  }
}