{
  "codigo_produto": "135",
  "url": "https://www.tdpwines.com.br/vinho-tinto-chileno-primus-the-blend",
  "titulo": "Primus The Blend 2020",
  "descricao_geral": "92 pontos Tim Atkin92 pontos James SucklingPrimus The Blend oferece um dos melhores custo-benefícios do Chile. É elaborado pela chilena Veramonte, mesma proprietária das marcas Ritual e Neyen, reconhecida pela seriedade no trabalho e comprometimento com a qualidade de seus vinhos. Este blend de tintas vem de Apalta, no vale de Colchagua, e utiliza uvas dos vinhedos centenários do fabuloso Neyen, um dos tintos mais consistentes e premiados do Chile.Seu corte muda em todas as safras, conforme a qualidade das uvas que encontram os enólogos. A safra atual, 2018, leva 55% de Cabernet Sauvignon, 20% de Carménère, 10% de Syrah, 10% de Petit Verdot e 5% de Cabernet Franc. Com excelentes 92 pontos de Tim Atkin, o vinho se destaca por sua profundidade, com muita fruta negra, como Cassis, e chocolate, envolvidos por notas terrosas e mentoladas. Assemelha-se muito a um bordeaux macio, carnoso e elegante.Dois terços do vinho passam 12 meses por barricas de carvalho francês, enquanto os outros 33% ficam em grandes foudres de 5000l. É um tinto de corpo e personalidade, com ótimo potecial de guarda e perfeito para acompanhar pratos à base de carne vermelha, especialmente os cozidos com molho, como um bom boeuf bourguignon. CaracteristicasProdutor VeramontePais ChileRegião ApaltaTipo TintoUva 55% Cabernet Sauvignon, 20% Carménère, 10% Syrah, 10% Petit Verdot, 5% Cabernet Franc.Volume 750mlSafra 2020Teor Alcoólico 13,5%Temperatura de Serviço 14 a 16°CVinificação Vinificação tradicional, fermentação com leveduras indígenas.Maturação 12 meses em barricas de carvalho francês (66%) e Foudres de Carvalho de 5000l (33%).Corpo IntensoPotencial de Guarda 7 a 10 anosHarmonizações Cozidos à base de carne vermelha, como boeuf bourguignon. Baixar Ficha Técnica Baixar Imagem",
  "caracteristicas": {
    "produtor": "Veramonte",
    "pais": "Ver País Argentina Patagonia Chile Portugal Brasil Espanha Ribera del Duero Itália Piemonte Abruzzo Sicilia Provincia de Taranto Toscana França África do Sul",
    "regiao": "Apalta",
    "tipo": "Tinto",
    "uva": "55% Cabernet Sauvignon, 20% Carménère, 10% Syrah, 10% Petit Verdot, 5% Cabernet Franc.",
    "volume_ml": 750,
    "safra": "2020",
    "teor_alcoolico_percent": 13.5,
    "temperatura_servico_c": "14 a 16°C",
    "vinificacao": "Vinificação tradicional, fermentação com leveduras indígenas.",
    "maturacao": "12 meses em barricas de carvalho francês (66%) e Foudres de Carvalho de 5000l (33%).",
    "corpo": "Intenso",
    "potencial_guarda_anos": "7 a 10 anos",
    "harmonizacoes": [
      "Cozidos à base de carne vermelha",
      "como boeuf bourguignon"
    ]
  },
  "midia": {
    "imagem_principal_url": "https://images.tcdn.com.br/img/img_prod/791130/primus_the_blend_2018_135_1_d9cba8223bff5a942767a928348ff59c_20221003162142.png",
    "ficha_tecnica_url": "https://drive.usercontent.google.com/u/2/uc?id=1O9Ocpw9VMJT_RNTmV2JLlONAMUnHTDju&export=download"
  }
}