{
  "codigo_produto": "289",
  "url": "https://www.tdpwines.com.br/vinho-branco-chileno-ola-po-chardonnay",
  "titulo": "Ola Po Chardonnay 2022",
  "descricao_geral": "Ola, poh! No Chile, o 'poh' é uma verdadeira insitituição nacional, uma gíria que faz parte do cotidiano do país. No Brasil, seria o equivalente ao 'bah' dos gaúchos, o 'oxe' dos baianos ou o infalível 'uai' mineiro. Ola Poh, mais que tudo, é um convite a experimentar um vinho incrível!Com 3.8 pontos no Vivino, uma nota sensacional para um vinho de menos de R$ 50 reais, sua primeira safra no Brasil esgotou rapidamente. Esta nova safra mantém todas as características do vinho anterior e, sobretudo, seu excelente custo-benefício.100% Chardonnay, este branco super refrescante é elaborado no vale de Curicó, mais especialmente em Bellavista, na sua parte mais alta, onde as os ventos frescos que descem da cordilheira tornam a zona muito propícia para a produção de excelentes brancos.Sem passagem por madeira, o foco é na expressão da fruta, e o que encontramos no vinho são notas cítricas, como limão siciliano e maçã verde, juntamente com alguns nuances florais. Em boca, é bastante direto, de acidez presente e equilibrada, que casa muito bem com seu corpo médio.Ola Po Chardonnay é perfeito para ser bebido só ou acompanhado de saladas, pratos leves ou peixes grelhados. CaracteristicasProdutor TDP WinesPais ChileRegião Valle de CuricóTipo BrancoUva 100% ChardonnayVolume 750mlSafra 2022Teor Alcoólico 13%Temperatura de Serviço 8 a 10°CVinificação Vinificação tradicional em tanques com controle de temperaturaMaturação Tanques de aço inoxCorpo MédioPotencial de Guarda 3 anosHarmonizações Peixes brancos grelhados, frango com molho branco Baixar Ficha Técnica Baixar Imagem",
  "caracteristicas": {
    "produtor": "TDP Wines",
    "pais": "Ver País Argentina Patagonia Chile Portugal Brasil Espanha Ribera del Duero Itália Piemonte Abruzzo Sicilia Provincia de Taranto Toscana França África do Sul",
    "regiao": "Valle de Curicó",
    "tipo": "Branco",
    "uva": "100% Chardonnay",
    "volume_ml": 750,
    "safra": "2022",
    "teor_alcoolico_percent": 13.0,
    "temperatura_servico_c": "8 a 10°C",
    "vinificacao": "Vinificação tradicional em tanques com controle de temperatura",
    "maturacao": "Tanques de aço inox",
    "corpo": "Médio",
    "potencial_guarda_anos": "3 anos",
    "harmonizacoes": [
      "Peixes brancos grelhados",
      "frango com molho branco"
    ]
  },
  "midia": {
    "imagem_principal_url": "https://images.tcdn.com.br/img/img_prod/791130/ola_po_chardonnay_2022_289_1_d43098de4b06f8fa599d179a25ca082e.png",
    "ficha_tecnica_url": "https://drive.usercontent.google.com/u/0/uc?id=13is6OB54hlyFxRL1zDrnk-9dRwaEs90q&export=download"
  }
}