{
  "codigo_produto": "vinho-tinto-argentino-finca-la-anita-gran-corte",
  "url": "https://www.tdpwines.com.br/vinho-tinto-argentino-finca-la-anita-gran-corte",
  "titulo": "Finca La Anita Gran Corte 2022Referência:101303Marca:Finca La AnitaSeja o primeiro a opinar",
  "descricao_geral": "Descrito por Tim Atkin como um belo exemplar da \"velha escola\" de Mendoza, o Gran Corte muda sua composição para esta safra 2022: sai a Syrah e entram Cabernet Sauvignon (20%), Petit Verdot (15%) e Cabernet Franc (10%), junto à 55% de Malbec. Este tinto apresenta aroma de especiarias, baunilha, café e frutas vermelhas. Encorpado, tem final longo, picante, onde sobressaem-se seus taninos finos e elegantes. Pode ser bebido agora ou guardado por mais de 10 anos. Pernil de cordeiro, moussaka e pratos ricos em especiarias são a companhia perfeita para este grande vinho! Caracteristicas Produtor Finca La Anita Pais Argentina Região Agrelo, Mendoza Tipo Tinto Uva 59% Syrah e 41% Malbec Volume 750ml Safra 2022 Teor Alcoólico 14,5% Temperatura de Serviço 16°C Vinificação Fermentação em tanques de inox com leveduras selecionadas. Fermentação malolática espontânea com controle de temperatura. Maturação 15 meses em barricas de carvalho francês Allier Corpo Encorpado Potencial de Guarda 7 anos Harmonizações Pernil de cordeiro, moussaka e pratos ricos em especiarias. Baixar Ficha Técnica Baixar Imagem",
  "caracteristicas": {
    "produtor": "Finca La Anita",
    "pais": "Ver País Argentina Patagonia Chile Portugal Brasil Espanha Ribera del Duero Itália Piemonte Abruzzo Sicilia Provincia de Taranto Toscana França África do Sul",
    "regiao": "Agrelo, Mendoza",
    "tipo": "Tinto",
    "uva": "59% Syrah e 41% Malbec",
    "volume_ml": 750,
    "safra": "2022",
    "teor_alcoolico_percent": 14.5,
    "temperatura_servico_c": "16°C",
    "vinificacao": "Fermentação em tanques de inox com leveduras selecionadas. Fermentação malolática espontânea com controle de temperatura.",
    "maturacao": "15 meses em barricas de carvalho francês Allier",
    "corpo": "Encorpado",
    "potencial_guarda_anos": "7 anos",
    "harmonizacoes": [
      "Pernil de cordeiro",
      "moussaka",
      "pratos ricos em especiarias"
    ]
  },
  "midia": {
    "imagem_principal_url": "https://images.tcdn.com.br/img/img_prod/791130/vin_arg_finca_la_anita_gran_corte_agrelo_red_blend_tto_6x750ml_93_1_4139528efef5ba6a817ad082129b820e_20221003162141.png",
    "ficha_tecnica_url": "https://drive.usercontent.google.com/u/2/uc?id=1EsHN9bVhU3831xF3Pwa1EzM65WxTWxZo&export=download"
  }
}