{
  "codigo_produto": "271",
  "url": "https://www.tdpwines.com.br/vinho-tinto-portugues-pedra-cancela-amplitude",
  "titulo": "Vinho Pedra Cancela Amplitude 2015",
  "descricao_geral": "18 pontos Vinho Grandes EscolhasO vinho português Amplitude é o ícone tinto da conhecida linha Pedra Cancela. O Dão, sua região de origem, é rodeada de altas montanhas, causando, em épocas de colheita, uma amplitude térmica que pode chegar a até 20 graus entre dias e noites.Esta diferença de temperatura não dá só nome como também característica ao vinho. Corte das tradicionais Touriga Nacional, Alfrocheiro e Tinta Roriz, todas de Vinhas Velhas com mais de 60 anos de idade, sua passagem de 12 meses por carvalho francês não o tira fruta e dá muita complexidade.No nariz, sentem-se notas de frutas vermelhas, pimenta, menta e bosque. Em boca, é um vinho de amplitude, onde a energia e seu ótimo corpo contrastam com a frescura. Seu final é muito longo e persistente.O Amplitude pode ser guardado com tranquilidade por mais de 10 anos. CaracteristicasProdutor LusoviniPais PortugalRegião DãoTipo TintoUva Touriga Nacional, Alfrocheiro e Tinta Roriz, todos de Vinhas VelhasVolume 750mlSafra 2015Teor Alcoólico 13%Temperatura de Serviço 16°CVinificação Desengace total, fermentação com parte da maceração em lagar de granito.Maturação 12 meses em barricas de carvalho francês.Corpo IntensoPotencial de Guarda 15 a 20 anosHarmonizações Pratos à base de carne, como boeuf bourguignon, chanfana e queijos de massa dura. Baixar Ficha Técnica Baixar Imagem",
  "caracteristicas": {
    "produtor": "Lusovini",
    "pais": "Ver País Argentina Patagonia Chile Portugal Brasil Espanha Ribera del Duero Itália Piemonte Abruzzo Sicilia Provincia de Taranto Toscana França África do Sul",
    "regiao": "Dão",
    "tipo": "Tinto",
    "uva": "Touriga Nacional, Alfrocheiro e Tinta Roriz, todos de Vinhas Velhas",
    "volume_ml": 750,
    "safra": "2015",
    "teor_alcoolico_percent": 13.0,
    "temperatura_servico_c": "16°C",
    "vinificacao": "Desengace total, fermentação com parte da maceração em lagar de granito.",
    "maturacao": "12 meses em barricas de carvalho francês.",
    "corpo": "Intenso",
    "potencial_guarda_anos": "15 a 20 anos",
    "harmonizacoes": [
      "Pratos à base de carne",
      "como boeuf bourguignon",
      "chanfana",
      "queijos de massa dura"
    ]
  },
  "midia": {
    "imagem_principal_url": "https://images.tcdn.com.br/img/img_prod/791130/vinho_pedra_cancela_amplitude_2013_271_1_7f3c4fb12f8d1b68a33252c06a36240f_20221003162146.png",
    "ficha_tecnica_url": "https://drive.usercontent.google.com/u/2/uc?id=1LSsflJwGx5rRKznVGBrzCs2dkrb4U1_W&export=download"
  }
}