{
  "codigo_produto": "493",
  "url": "https://www.tdpwines.com.br/vinhos/vinho-branco-pedra-cancela-vinha-da-fidalga-cerceal-branco-dao-doc",
  "titulo": "Vinho Branco Pedra Cancela Vinha da Fidalga Cerceal Branco Dão DOC",
  "descricao_geral": "Produzido pela Lusovini, referência em vinhos autênticos de Portugal, o Pedra Cancela Cerceal Branco nasce da exclusiva Vinha da Fidalga, dedicada ao resgate das variedades autóctones da região do Dão. Elaborado 100% com uvas Cerceal Branco, colhidas cuidadosamente, este vinho branco surpreende pela elegância exótica de aromas intensos, destacando lichia, maçã fresca e vibrantes frutas cítricas.Em boca, destaca-se pela textura untuosa, corpo médio e sabor marcante, equilibrado por uma acidez refrescante que prolonga sua persistência. Seu potencial de guarda entre 6 a 8 anos reforça sua atratividade como investimento seguro para estabelecimentos que buscam diferenciação e qualidade comprovada. CaracteristicasProdutor LusoviniPais PortugalRegião DãoTipo Branco100% Cerceal BrancoVolume 750mlSafra 2022Teor Alcoólico 11,5%Temperatura de Serviço 8 a 10°CVinificação Fermentação com temperatura Controlada a 14 - 16ºCMaturação Tanques de aço inox.Corpo: MédioPotencial de Guarda: 6 a 8 anosHarmonizações Carnes brancas, peixes e saladas. Baixar Ficha Técnica Baixar Imagem",
  "caracteristicas": {
    "produtor": "Lusovini",
    "pais": "Ver País Argentina Patagonia Chile Portugal Brasil Espanha Ribera del Duero Itália Piemonte Abruzzo Sicilia Provincia de Taranto Toscana França África do Sul",
    "regiao": "Dão",
    "tipo": "Branco",
    "uva": null,
    "volume_ml": 750,
    "safra": "2022",
    "teor_alcoolico_percent": 11.5,
    "temperatura_servico_c": "8 a 10°C",
    "vinificacao": "Fermentação com temperatura Controlada a 14 - 16ºC",
    "maturacao": "Tanques de aço inox.",
    "corpo": null,
    "potencial_guarda_anos": null,
    "harmonizacoes": [
      "Carnes brancas",
      "peixes",
      "saladas"
    ]
  },
  "midia": {
    "imagem_principal_url": "https://images.tcdn.com.br/img/img_prod/791130/vinho_branco_pedra_cancela_vinha_da_fidalga_cerceal_branco_dao_doc_493_1_ba733463ce047da14fa4bf8577fd9bf2.png",
    "ficha_tecnica_url": "https://drive.google.com/file/d/1076-bVUoeSd25Eh1rbIdQ-Gw5xq42TOy/view?usp=sharing"
  }
}