{
  "codigo_produto": "287",
  "url": "https://www.tdpwines.com.br/vinho-tinto-chileno-neyen-espiritu-de-apalta-malbec",
  "titulo": "Neyen Limited Edition Malbec 2019",
  "descricao_geral": "Um surpreendente Malbec chileno, Neyen Espiritú de Apalta Limited Edition conquistou, nos últimos anos, um grande sucesso entre críticos e apreciadores de grandes tintos do Chile, figurando na lista dos melhores vinhos do país e atingindo até mesmo espetaculares 100 pontos do crítico James Suckling.O parque de vinhas da Neyen em Apalta é uma coleção única de plantas que contam a história da vitivinicultura chilena. Lá, plantas de Malbec, Cabernet Sauvignon e Carménère de até 130 anos de idade, certificadamente orgânicas e cultivadas sob preceitos biodinâmicos, dão origem a vinhos profundos e extremamente complexos.Esta edição limitada de 1512 garrafas, da quais apenas 42 vieram ao Brasil, utiliza as vinhas de Malbec, as mais raras da plantação. Com passagem de 12 meses por barricas de carvalho francês, o vinho, no nariz, mostra notas de fruta negra e vermelha, especialmente cerejas, junto à presença de especiarias e um agradável floral, de violeta.Em boca, é um vinho que une a potência que seria esperada de um vinho originado destes vinhedos de baixo rendimento junto a uma acidez muito interessante, que lhe dá equilíbrio e convida a beber a próxima taça. É um grande vinho para ser bebido agora ou guardado com certeza por mais de 10 anos. CaracteristicasProdutor VeramontePais ChileRegião Apalta, no Vale de ColcháguaTipo TintoUva Malbec de vinhas velhas orgânicas e biodinâmicas com até 130 anos de idade.Volume 750mlSafra 2019Teor Alcoólico 13,5%Temperatura de Serviço 16°CVinificação Colheita e seleção manual das uvas. Fermentação com leveduras nativas em tanques com temperatura controlada (26ºC) e 8 a 10 dias de maceração com as cascasMaturação 12 meses em barricas de carvalho francês 50% novas.Corpo EncorpadoPotencial de Guarda 15 anosHarmonizações Cordeiro assado, carnes de caça de pelo, churrasco Baixar Ficha Técnica Baixar Imagem",
  "caracteristicas": {
    "produtor": "Veramonte",
    "pais": "Ver País Argentina Patagonia Chile Portugal Brasil Espanha Ribera del Duero Itália Piemonte Abruzzo Sicilia Provincia de Taranto Toscana França África do Sul",
    "regiao": "Apalta, no Vale de Colchágua",
    "tipo": "Tinto",
    "uva": "Malbec de vinhas velhas orgânicas e biodinâmicas com até 130 anos de idade.",
    "volume_ml": 750,
    "safra": "2019",
    "teor_alcoolico_percent": 13.5,
    "temperatura_servico_c": "16°C",
    "vinificacao": "Colheita e seleção manual das uvas. Fermentação com leveduras nativas em tanques com temperatura controlada (26ºC) e 8 a 10 dias de maceração com as cascas",
    "maturacao": "12 meses em barricas de carvalho francês 50% novas.",
    "corpo": "Encorpado",
    "potencial_guarda_anos": "15 anos",
    "harmonizacoes": [
      "Cordeiro assado",
      "carnes de caça de pelo",
      "churrasco"
    ]
  },
  "midia": {
    "imagem_principal_url": "https://images.tcdn.com.br/img/img_prod/791130/neyen_limited_edition_malbec_2019_287_1_a62f68f1a78ea12f3eb39f67fe232a3f_20221003162148.png",
    "ficha_tecnica_url": "https://drive.usercontent.google.com/u/2/uc?id=1Ixc72VfeSA1hfrOKqptBVrXphSmYtuLf&export=download"
  }
}