{
  "codigo_produto": "185",
  "url": "https://www.tdpwines.com.br/vinho-tinto-portugues-pedra-cancela-selecao-do-enologo-1500ml",
  "titulo": "Pedra Cancela Seleção do Enólogo Tinto 2018 1500ml",
  "descricao_geral": "No Dão, Pedra Cancela já pode ser considerada um novo ícone regional. Para Pedro Garcias, do Público, de Portugal, seus vinhos, em especial os tintos, expressam como poucos o terroir desta zona central e de muita importância para o vinho português. Os solos graníticos e a região com altas variações de temperatura entre o dia e a noite originam vinhos extremamente complexos e elegantes.Com leve passagem por madeira, o Pedra Cancela Seleção do Enólogo propõe um perfil mais moderno do Dão sem abdicar da tradição. Corte das variedades Touriga Nacional, Tinta Roriz e Alfrocheiro, é intenso, com notas de ameixa madura e toques de cacau. Sua estrutura faz com que acompanhe muito bem pratos de carne vermelha assada.Nesta garrafa Magnum, você leva 1,5 litro de um excelente vinho da safra 2015, sempre lembrando que os vinhos em garrafa Magnum são mais longevos, pois a troca de oxigênio é menor e faz com que o líquido amadureça de forma mais lenta. CaracteristicasProdutor LusoviniPais PortugalRegião DãoTipo TintoUva Touriga Nacional, Tinta Roriz e AlfrocheiroVolume 1500mlSafra 2018Teor Alcoólico 13%Temperatura de Serviço 14 a 16°CVinificação Fermentação a temperatura controlada entre 24 e 26ºC.Maturação 6 meses em barricas de carvalho francês.Corpo MédioPotencial de Guarda 10 anosHarmonizações Carnes vermelhas e queijos de massa mole. Baixar Ficha Técnica Baixar Imagem",
  "caracteristicas": {
    "produtor": "Lusovini",
    "pais": "Ver País Argentina Patagonia Chile Portugal Brasil Espanha Ribera del Duero Itália Piemonte Abruzzo Sicilia Provincia de Taranto Toscana França África do Sul",
    "regiao": "Dão",
    "tipo": "Tinto",
    "uva": "Touriga Nacional, Tinta Roriz e Alfrocheiro",
    "volume_ml": 1500,
    "safra": "2018",
    "teor_alcoolico_percent": 13.0,
    "temperatura_servico_c": "14 a 16°C",
    "vinificacao": "Fermentação a temperatura controlada entre 24 e 26ºC.",
    "maturacao": "6 meses em barricas de carvalho francês.",
    "corpo": "Médio",
    "potencial_guarda_anos": "10 anos",
    "harmonizacoes": [
      "Carnes vermelhas",
      "queijos de massa mole"
    ]
  },
  "midia": {
    "imagem_principal_url": "https://images.tcdn.com.br/img/img_prod/791130/pedra_cancela_selecao_do_enologo_tinto_2015_1500ml_185_1_0509f724b37f2aa609465e316d1c7472_20221003162142.png",
    "ficha_tecnica_url": "https://drive.usercontent.google.com/u/2/uc?id=1LlsuY2qgF-S-wjWdAEVZYiEKsUuviybA&export=download"
  }
}