{
  "codigo_produto": "387",
  "url": "https://www.tdpwines.com.br/vinho-tinto-chileno-ola-po-cabernet-sauvignon",
  "titulo": "Ola Po Cabernet Sauvignon Tinto 2022",
  "descricao_geral": "Cabernet Sauvignon de muita tipicidade, com notas de frutas negras, como cassis e mirtilo, e um toque de ervas frescas. Em boca, tem corpo médio, taninos presentes mas macios e final de média intensidade. CaracteristicasProdutor TDP WinesPais ChileRegião Valle CentralTipo TintoUva 100% Cabernet SauvignonVolume 750mlSafra 2022Teor Alcoólico 13%Temperatura de Serviço 12 a 14°CVinificação Vinificação tradicional em tanques com controle de temperaturaMaturação Tanques de aço inoxCorpo MédioPotencial de Guarda 3 a 5 anosHarmonizações Carnes vermelhas grelhadas, queijos de massa média, carnes braseadas. Baixar Ficha Técnica Baixar Imagem",
  "caracteristicas": {
    "produtor": "TDP Wines",
    "pais": "Ver País Argentina Patagonia Chile Portugal Brasil Espanha Ribera del Duero Itália Piemonte Abruzzo Sicilia Provincia de Taranto Toscana França África do Sul",
    "regiao": "Valle Central",
    "tipo": "Tinto",
    "uva": "100% Cabernet Sauvignon",
    "volume_ml": 750,
    "safra": "2022",
    "teor_alcoolico_percent": 13.0,
    "temperatura_servico_c": "12 a 14°C",
    "vinificacao": "Vinificação tradicional em tanques com controle de temperatura",
    "maturacao": "Tanques de aço inox",
    "corpo": "Médio",
    "potencial_guarda_anos": "3 a 5 anos",
    "harmonizacoes": [
      "Carnes vermelhas grelhadas",
      "queijos de massa média",
      "carnes braseadas"
    ]
  },
  "midia": {
    "imagem_principal_url": "https://images.tcdn.com.br/img/img_prod/791130/ola_po_cabernet_sauvignon_tinto_2022_387_1_530b6a91457abb4b8d5a490977495a30.png",
    "ficha_tecnica_url": "https://drive.usercontent.google.com/uc?id=1KWj3C49WtEp7B-nxXCbwXsNM5mLKByKS&export=download"
  }
}