{
  "codigo_produto": "209",
  "url": "https://www.tdpwines.com.br/vinho-tinto-argentino-tapiz-las-notas-de-jean-claude-blend",
  "titulo": "Tapiz Las Notas de Jean Claude 2019",
  "descricao_geral": "95 pontos Robert Parker94 pontos James Suckling93 pontos DescorchadosUm ícone argentino, Las Notas de Jean Claude reflete o trabalho do enólogo Jean Claude Berrouet, enólogo-chefe do mítico Chateau Petrus por 44 anos, junto à Tapiz. O vinho volta ao Brasil, de forma oficial, pela importadora TDP Wines!Berrouet merece uma introdução à parte. O Francês é mundialmente reconhecido por ter elevado a Petrus à marca de um dos vinhos mais desejados, reverenciados e caros do mundo. Seu trabalho com a casta Merlot é amplamente reconhecido, tendo sido premiado com o troféu Winemakers? Winemaker (o ?Enólogo dos Enólogos) pelo Instituto dos Masters of Wine (IMW) em 2018.E é justamente de Merlot que Las Notas de Jean Claude é principalmente elaborado. Prestando consultoria à Tapiz desde 2012, Jean Claude, juntamente ao enólogo da casa, Fabian Valenzuela, utilizaram toda a sua experiência neste vinho feito com as uvas do vinhedo San Pablo, a 1350 metros de altitude.Além da Merlot, o corte é composto por Cabernet Franc (12%) e Petit Verdot (4%), variedades tipicamente bordalesas. O vinho é elaborado de forma bastante tradicional, com leveduras selecionadas mas mínimas intervenções, e passa 11 meses em barricas de carvalho francês novas.Complexo e elegante, Las Notas tem um nariz bastante sutil, com as tradicionais notas de cassis e ameixa, juntamente a toques de chocolate e cacau. Tem a elegância de um verdadeiro Bordeaux por uma fração do preço de um Petrus.Recomendamos beber agora ou guardar pelos próximos 10 a 15 anos. CaracteristicasProdutor TapizPais ArgentinaRegião San Pablo, MendozaTipo TintoUva Merlot (84%), Cabernet Franc (12%), Petit Verdot (4%)Volume 750mlSafra 2019Teor Alcoólico 14,4%Temperatura de Serviço 16°CVinificação Fermentação tradicional em tanques de aço inox a 28ºC por 12 dias. Leveduras selecionadas.Maturação 11 meses em barricas de carvalho francês novas.Corpo IntensoPotencial de Guarda 10 anosHarmonizações Cordeiro grelhado, Lombo de porco com molho oriental, queijos de massa dura. Baixar Ficha Técnica Baixar Imagem",
  "caracteristicas": {
    "produtor": "Tapiz",
    "pais": "Ver País Argentina Patagonia Chile Portugal Brasil Espanha Ribera del Duero Itália Piemonte Abruzzo Sicilia Provincia de Taranto Toscana França África do Sul",
    "regiao": "San Pablo, Mendoza",
    "tipo": "Tinto",
    "uva": "Merlot (84%), Cabernet Franc (12%), Petit Verdot (4%)",
    "volume_ml": 750,
    "safra": "2019",
    "teor_alcoolico_percent": 14.4,
    "temperatura_servico_c": "16°C",
    "vinificacao": "Fermentação tradicional em tanques de aço inox a 28ºC por 12 dias. Leveduras selecionadas.",
    "maturacao": "11 meses em barricas de carvalho francês novas.",
    "corpo": "Intenso",
    "potencial_guarda_anos": "10 anos",
    "harmonizacoes": [
      "Cordeiro grelhado",
      "Lombo de porco com molho oriental",
      "queijos de massa dura"
    ]
  },
  "midia": {
    "imagem_principal_url": "https://images.tcdn.com.br/img/img_prod/791130/tapiz_las_notas_de_jean_claude_2014_209_1_7f0c9973c78353c6dfe613c70efc7147_20221003162145.png",
    "ficha_tecnica_url": "https://drive.usercontent.google.com/u/2/uc?id=1Hi6UkiWyGO3BIQz8egKUFW4PPxcpGffX&export=download"
  }
}