{
  "codigo_produto": "177",
  "url": "https://www.tdpwines.com.br/vinho-tinto-argentino-luna-reserva-malbec",
  "titulo": "Luna Reserva Malbec 2020",
  "descricao_geral": "O Reserva Malbec é o mais recente lançamento da linha Luna, os vinhos &#39;jovens&#39; de Finca La Anita. &#39;Jovem&#39;, entre aspas, pois é difícil conceituar este grande vinho. Single vineyard, com uvas provenientes de Agrelo, no terreno vizinho à famosa Catena Zapata, Luna mantém a tradição da vinícola de elaborar vinhos da maneira tradicional mendoncina, bastante típicos, terrosos e potentes.Este Reserva é um passo além em concentração e potência em relação aos já conhecidos varietais da linha Luna. Mantém a ótima tipicidade característica dos Finca La Anita, apresentando aromas de cassis, passas e amoras, com notas de caramelo e baunilha típicas da passagem por madeira. Típico Malbec de Agrelo, no coração de Mendoza, é carnoso, com excelente estrutura e ideal para acompanhar pratos à base de carne vermelha, como entrecot assado na parrilla.Com 12 meses em barricas de carvalho novas e usadas, é longevo e ainda pode ser guardado na sua adega por muitos anos, apesar de pronto para beber. CaracteristicasProdutor Finca La AnitaPais ArgentinaRegião Agrelo, MendozaTipo TintoUva 100% MalbecVolume 750mlSafra 2020Teor Alcoólico 13,5%Temperatura de Serviço 16°CVinificação Fermentação em tanques de inox com leveduras selecionadas. Fermentação malolática espontânea com controle de temperatura.Maturação 12 meses em barricas francesas e americanas.Corpo EncorpadoPotencial de Guarda 7 anosHarmonizações Carnes grelhadas como costela, ensopados de carne e carnes de caça. Baixar Ficha Técnica Baixar Imagem",
  "caracteristicas": {
    "produtor": "Finca La Anita",
    "pais": "Ver País Argentina Patagonia Chile Portugal Brasil Espanha Ribera del Duero Itália Piemonte Abruzzo Sicilia Provincia de Taranto Toscana França África do Sul",
    "regiao": "Agrelo, Mendoza",
    "tipo": "Tinto",
    "uva": "100% Malbec",
    "volume_ml": 750,
    "safra": "2020",
    "teor_alcoolico_percent": 13.5,
    "temperatura_servico_c": "16°C",
    "vinificacao": "Fermentação em tanques de inox com leveduras selecionadas. Fermentação malolática espontânea com controle de temperatura.",
    "maturacao": "12 meses em barricas francesas e americanas.",
    "corpo": "Encorpado",
    "potencial_guarda_anos": "7 anos",
    "harmonizacoes": [
      "Carnes grelhadas como costela",
      "ensopados de carne",
      "carnes de caça"
    ]
  },
  "midia": {
    "imagem_principal_url": "https://images.tcdn.com.br/img/img_prod/791130/luna_reserva_malbec_2018_177_1_975f30deb3fbeb3902ce915fba2919ed_20221003162142.png",
    "ficha_tecnica_url": "https://drive.usercontent.google.com/u/2/uc?id=1Em0qGbGQP8ktUlurPItrTiQKT-yd71Jb&export=download"
  }
}