{
  "codigo_produto": "131",
  "url": "https://www.tdpwines.com.br/vinho-tinto-chileno-primus-cabernet-sauvignon",
  "titulo": "Primus Cabernet Sauvignon 2020",
  "descricao_geral": "Primus é elaborado pela chilena Veramonte, mesma proprietária das marcas Ritual e Neyen, reconhecida pela seriedade no trabalho e comprometimento com a qualidade de seus vinhos. Este Cabernet Sauvignon vem do Vale de Maipo, região reconhecida pela qualidade de seus vinhos varietais e que tem ótimas expressões da Cabernet Sauvignon.Este varietal de 93 pontos Tim Atkin destaca-se pela intensidade equilíbrio, com textura sedosa e taninos presentes, mas polidos e redondos. Seu rico aroma apresenta notas de amora e cereja, juntamente com baunilha e cedro. É um excelente exemplar da Cabernet Sauvignon, ótimo para os amantes da casta.Com 12 meses em barricas de carvalho francês (18% novas), é um CS ideal para acompanhar pratos à base de carne vermelha, especialmente o nosso tradicional churrasco. CaracteristicasProdutor VeramontePais ChileRegião MaipoTipo TintoUva 100% Cabernet SauvignonVolume 750mlSafra 2020Teor Alcoólico 13,5%Temperatura de Serviço 14 a 16°CVinificação Vinificação tradicional, fermentação com leveduras indígenas.Maturação 12 meses em barricas de carvalho francês (18% novas).Corpo IntensoPotencial de Guarda 8 anosHarmonizações Contrafilé grelhado, costela assada na brasa. Baixar Ficha Técnica Baixar Imagem",
  "caracteristicas": {
    "produtor": "Veramonte",
    "pais": "Ver País Argentina Patagonia Chile Portugal Brasil Espanha Ribera del Duero Itália Piemonte Abruzzo Sicilia Provincia de Taranto Toscana França África do Sul",
    "regiao": "Maipo",
    "tipo": "Tinto",
    "uva": "100% Cabernet Sauvignon",
    "volume_ml": 750,
    "safra": "2020",
    "teor_alcoolico_percent": 13.5,
    "temperatura_servico_c": "14 a 16°C",
    "vinificacao": "Vinificação tradicional, fermentação com leveduras indígenas.",
    "maturacao": "12 meses em barricas de carvalho francês (18% novas).",
    "corpo": "Intenso",
    "potencial_guarda_anos": "8 anos",
    "harmonizacoes": [
      "Contrafilé grelhado",
      "costela assada na brasa"
    ]
  },
  "midia": {
    "imagem_principal_url": "https://images.tcdn.com.br/img/img_prod/791130/primus_cabernet_sauvignon_2019_131_1_5903f35cb7af0c4732ae5cec43399ecf_20221003162142.png",
    "ficha_tecnica_url": "https://drive.usercontent.google.com/u/2/uc?id=1O5InUIm0H1giLhJjAdBDpIU0Le-8rAlx&export=download"
  }
}