{
  "codigo_produto": "143",
  "url": "https://www.tdpwines.com.br/vinho-tinto-argentino-gen-del-alma-seminare-malbec",
  "titulo": "Gen del Alma Seminare Malbec 2016",
  "descricao_geral": "99 pontos Descorchados - melhor Malbec e melhor tinto do Guia em 201896 pontos Robert ParkerSimplesmente o melhor tinto do Guia Descorchados de 2018, Seminare Malbec é uma verdadeira jóia bruta. É elaborado na altitude de Gualtallay, no Valle do Uco, pela Gen del Alma, uma inovadora e inquieta vinícola com menos de 10 anos de idade que se destaca pela mescla de ousadia e extrema capacidade de sua equipe enológica.O vinho é elaborado para ser a pura expressão da Malbec. Feito 100% com a variedade, a uva vai de uma breve fermentação em ânforas de cimento, sendo 60% da fruta com cachos, à barricas de 500 litros de quinto uso, que dão mais estrutura ao vinho e menos aporte de taninos e aromas terciários. As uvas vêm de vinhedos a 1400m de altitude e solos aluvionais e calcários, de baixíssimo rendimento. A pureza que falamos há pouco se explica pela intervenção enológica praticamente zero: há fruta, da melhor qualidade, e nada mais.O vinho é espetacular, maravilhoso, e precisa ser compreendido por quem o degusta. Linear, fresco e elegante, seus sabores são, na maioria, bastante frescos, com destaque para as notas de cerejas e violetas, amalgamadas por um toque mineral muito interessante.Seu frescor e estrutura o fazem par perfeito para assados, massas com molho vermelho e queijos fortes como o Grana. CaracteristicasProdutor Gen Del AlmaPais ArgentinaRegião Vale de Tupungato, MendozaTipo TintoUva 100% MalbecVolume 750mlSafra 2016Teor Alcoólico 13%Temperatura de Serviço 14 a 16°CVinificação Fermentação em ânforas de concreto a baixa temperatura com 60% dos cachos inteiros. Sem remontagem.Maturação Estágio em barricas de carvalho francês de quinto uso.Corpo IntensoPotencial de Guarda 7 a 10 anosHarmonizações Carnes vermelhas assadas, massas com molhos vermelhos, queijos fortes. Baixar Ficha Técnica Baixar Imagem",
  "caracteristicas": {
    "produtor": "Gen Del Alma",
    "pais": "Ver País Argentina Patagonia Chile Portugal Brasil Espanha Ribera del Duero Itália Piemonte Abruzzo Sicilia Provincia de Taranto Toscana França África do Sul",
    "regiao": "Vale de Tupungato, Mendoza",
    "tipo": "Tinto",
    "uva": "100% Malbec",
    "volume_ml": 750,
    "safra": "2016",
    "teor_alcoolico_percent": 13.0,
    "temperatura_servico_c": "14 a 16°C",
    "vinificacao": "Fermentação em ânforas de concreto a baixa temperatura com 60% dos cachos inteiros. Sem remontagem.",
    "maturacao": "Estágio em barricas de carvalho francês de quinto uso.",
    "corpo": "Intenso",
    "potencial_guarda_anos": "7 a 10 anos",
    "harmonizacoes": [
      "Carnes vermelhas assadas",
      "massas com molhos vermelhos",
      "queijos fortes"
    ]
  },
  "midia": {
    "imagem_principal_url": "https://images.tcdn.com.br/img/img_prod/791130/gen_del_alma_seminare_malbec_2016_143_1_20221003162142.png",
    "ficha_tecnica_url": "https://drive.google.com/u/0/uc?id=1R6TM_OwLUne7ZPpvXJp8f4qZhbJnJYaX&export=download"
  }
}